{"042-0901":["JP","042-0901","Gabinocho","Hokkaido","12","Hakodate Shi","2130184","","","42.1447","141.5093","1"],"042-0902":["JP","042-0902","Tetsuzancho","Hokkaido","12","Hakodate Shi","2130184","","","42.1447","141.5093","1"],"042-0903":["JP","042-0903","Higashihatacho","Hokkaido","12","Hakodate Shi","2130184","","","42.1447","141.5093","1"],"042-0904":["JP","042-0904","Ioharacho","Hokkaido","12","Hakodate Shi","2130184","","","42.1447","141.5093","1"],"042-0905":["JP","042-0905","Momijiyamacho","Hokkaido","12","Hakodate Shi","2130184","","","42.1447","141.5093","1"],"042-0906":["JP","042-0906","Mitsumoricho","Hokkaido","12","Hakodate Shi","2130184","","","42.1447","141.5093","1"],"042-0907":["JP","042-0907","Masukawacho","Hokkaido","12","Hakodate Shi","2130184","","","42.1447","141.5093","1"],"042-0908":["JP","042-0908","Dozancho","Hokkaido","12","Hakodate Shi","2130184","","","42.1447","141.5093","1"],"042-0911":["JP","042-0911","Ishikuracho","Hokkaido","12","Hakodate Shi","2130184","","","41.8372","140.9257","4"],"042-0912":["JP","042-0912","Nakanocho","Hokkaido","12","Hakodate Shi","2130184","","","42.15","140.4667","1"],"042-0913":["JP","042-0913","Akasakacho","Hokkaido","12","Hakodate Shi","2130184","","","42.15","140.4667","1"],"042-0914":["JP","042-0914","Kamiyunokawacho","Hokkaido","12","Hakodate Shi","2130184","","","42.15","140.4667","1"],"042-0915":["JP","042-0915","Nishiasahiokacho","Hokkaido","12","Hakodate Shi","2130184","","","42.15","140.4667","1"],"042-0916":["JP","042-0916","Asahiokacho","Hokkaido","12","Hakodate Shi","2130184","","","42.15","140.4667","1"],"042-0917":["JP","042-0917","Kameocho","Hokkaido","12","Hakodate Shi","2130184","","","42.15","140.4667","1"],"042-0918":["JP","042-0918","Maiharacho","Hokkaido","12","Hakodate Shi","2130184","","","42.15","140.4667","1"],"042-0921":["JP","042-0921","Shimminatocho","Hokkaido","12","Hakodate Shi","2130184","","","42.1447","141.5093","1"],"042-0922":["JP","042-0922","Zenikamecho","Hokkaido","12","Hakodate Shi","2130184","","","42.1447","141.5093","1"],"042-0923":["JP","042-0923","Shinoricho","Hokkaido","12","Hakodate Shi","2130184","","","42.1447","141.5093","1"],"042-0924":["JP","042-0924","Nesakicho","Hokkaido","12","Hakodate Shi","2130184","","","42.1447","141.5093","1"],"042-0931":["JP","042-0931","Enomotocho","Hokkaido","12","Hakodate Shi","2130184","","","41.7833","140.7833","1"],"042-0932":["JP","042-0932","Yunokawacho","Hokkaido","12","Hakodate Shi","2130184","","","41.7833","140.7833","4"],"042-0933":["JP","042-0933","Yunohamacho","Hokkaido","12","Hakodate Shi","2130184","","","41.7833","140.7833","1"],"042-0934":["JP","042-0934","Hironocho","Hokkaido","12","Hakodate Shi","2130184","","","41.8372","140.9257","1"],"042-0935":["JP","042-0935","Komabacho","Hokkaido","12","Hakodate Shi","2130184","","","41.8372","140.9257","1"],"042-0941":["JP","042-0941","Fukaboricho","Hokkaido","12","Hakodate Shi","2130184","","","42.5008","143.2779","1"],"042-0942":["JP","042-0942","Kashiwagicho","Hokkaido","12","Hakodate Shi","2130184","","","41.8372","140.9257","4"],"042-0943":["JP","042-0943","Nogimachi","Hokkaido","12","Hakodate Shi","2130184","","","42.5008","143.2779","1"],"042-0944":["JP","042-0944","Kanahoricho","Hokkaido","12","Hakodate Shi","2130184","","","42.5008","143.2779","1"],"042-0951":["JP","042-0951","Setogawacho","Hokkaido","12","Hakodate Shi","2130184","","","42.1447","141.5093","1"],"042-0952":["JP","042-0952","Takamatsucho","Hokkaido","12","Hakodate Shi","2130184","","","42.1447","141.5093","1"],"042-0953":["JP","042-0953","Tokuracho","Hokkaido","12","Hakodate Shi","2130184","","","42.1447","141.5093","1"],"042-0954":["JP","042-0954","Uenocho","Hokkaido","12","Hakodate Shi","2130184","","","42.1447","141.5093","1"],"042-0955":["JP","042-0955","Takaokacho","Hokkaido","12","Hakodate Shi","2130184","","","42.1447","141.5093","1"],"042-0956":["JP","042-0956","Miharashicho","Hokkaido","12","Hakodate Shi","2130184","","","42.1447","141.5093","1"],"042-0957":["JP","042-0957","Takisawacho","Hokkaido","12","Hakodate Shi","2130184","","","42.1447","141.5093","1"],"042-0958":["JP","042-0958","Suzuranokacho","Hokkaido","12","Hakodate Shi","2130184","","","42.1447","141.5093","1"]}