{"289-0301":["JP","289-0301","Ichinowakeme","Chiba Ken","04","Katori Shi","2111171","","","35.8667","140.6","1"],"289-0302":["JP","289-0302","Sannowakeme","Chiba Ken","04","Katori Shi","2111171","","","35.8667","140.6","1"],"289-0303":["JP","289-0303","Tomita","Chiba Ken","04","Katori Shi","2111171","","","35.8667","140.6","4"],"289-0304":["JP","289-0304","Shimokobori","Chiba Ken","04","Katori Shi","2111171","","","35.8667","140.6","1"],"289-0305":["JP","289-0305","Wakarego","Chiba Ken","04","Katori Shi","2111171","","","35.8667","140.6","1"],"289-0306":["JP","289-0306","Kamikobori","Chiba Ken","04","Katori Shi","2111171","","","35.8667","140.6","1"],"289-0307":["JP","289-0307","Mashita","Chiba Ken","04","Katori Shi","2111171","","","35.8667","140.6","1"],"289-0308":["JP","289-0308","Kinochimushihatakamikoboriiriaichio","Chiba Ken","04","Katori Shi","2111171","","","35.8667","140.6","1"],"289-0311":["JP","289-0311","Yokaichiba","Chiba Ken","04","Katori Shi","2111171","","","35.8535","140.5401","4"],"289-0312":["JP","289-0312","Hongo","Chiba Ken","04","Katori Shi","2111171","","","35.8535","140.5401","4"],"289-0313":["JP","289-0313","Omigawa","Chiba Ken","04","Katori Shi","2111171","","","35.85","140.6167","4"],"289-0314":["JP","289-0314","Noda","Chiba Ken","04","Katori Shi","2111171","","","35.8535","140.5401","4"],"289-0321":["JP","289-0321","Atamagawa","Chiba Ken","04","Katori Shi","2111171","","","35.5181","139.9152","1"],"289-0322":["JP","289-0322","Shimoiida","Chiba Ken","04","Katori Shi","2111171","","","35.5181","139.9152","1"],"289-0323":["JP","289-0323","Okaiida","Chiba Ken","04","Katori Shi","2111171","","","35.5181","139.9152","1"],"289-0324":["JP","289-0324","Izumi","Chiba Ken","04","Katori Shi","2111171","","","35.8535","140.5401","4"],"289-0325":["JP","289-0325","Kaizuka","Chiba Ken","04","Katori Shi","2111171","","","35.8535","140.5401","4"],"289-0326":["JP","289-0326","Atamadai","Chiba Ken","04","Katori Shi","2111171","","","35.5181","139.9152","1"],"289-0327":["JP","289-0327","Kubo","Chiba Ken","04","Katori Shi","2111171","","","35.8535","140.5401","4"],"289-0328":["JP","289-0328","Gogochi","Chiba Ken","04","Katori Shi","2111171","","","35.5181","139.9152","1"],"289-0329":["JP","289-0329","Funo","Chiba Ken","04","Katori Shi","2111171","","","35.5181","139.9152","1"],"289-0331":["JP","289-0331","Hanegawa","Chiba Ken","04","Katori Shi","2111171","","","35.3164","140.0491","1"],"289-0332":["JP","289-0332","Minamiharachishinden","Chiba Ken","04","Katori Shi","2111171","","","35.3164","140.0491","1"],"289-0333":["JP","289-0333","Iriaichi","Chiba Ken","04","Katori Shi","2111171","","","35.3164","140.0491","1"],"289-0334":["JP","289-0334","Kawagashira","Chiba Ken","04","Katori Shi","2111171","","","35.3164","140.0491","1"],"289-0335":["JP","289-0335","Kitaharachishinden","Chiba Ken","04","Katori Shi","2111171","","","35.3164","140.0491","1"],"289-0336":["JP","289-0336","Shinshinden","Chiba Ken","04","Katori Shi","2111171","","","35.3164","140.0491","1"],"289-0337":["JP","289-0337","Kinochi","Chiba Ken","04","Katori Shi","2111171","","","35.3164","140.0491","1"],"289-0338":["JP","289-0338","Shimogawa","Chiba Ken","04","Katori Shi","2111171","","","35.8535","140.5401","4"],"289-0341":["JP","289-0341","Mushihata","Chiba Ken","04","Katori Shi","2111171","","","35.5789","140.2185","1"],"289-0342":["JP","289-0342","Ryuzaku","Chiba Ken","04","Katori Shi","2111171","","","35.5789","140.2185","1"],"289-0343":["JP","289-0343","Yamagawa","Chiba Ken","04","Katori Shi","2111171","","","35.5789","140.2185","1"],"289-0344":["JP","289-0344","Shirai","Chiba Ken","04","Katori Shi","2111171","","","35.5789","140.2185","1"],"289-0345":["JP","289-0345","Hachihon","Chiba Ken","04","Katori Shi","2111171","","","35.5789","140.2185","1"],"289-0346":["JP","289-0346","Aburata","Chiba Ken","04","Katori Shi","2111171","","","35.5789","140.2185","1"],"289-0347":["JP","289-0347","Hatahoko","Chiba Ken","04","Katori Shi","2111171","","","35.5789","140.2185","1"],"289-0348":["JP","289-0348","Orihata","Chiba Ken","04","Katori Shi","2111171","","","35.5789","140.2185","1"],"289-0349":["JP","289-0349","Uchino","Chiba Ken","04","Katori Shi","2111171","","","35.5789","140.2185","1"],"289-0401":["JP","289-0401","Komenoi","Chiba Ken","04","Katori Shi","2111171","","","35.3327","140.1251","1"],"289-0402":["JP","289-0402","Omi","Chiba Ken","04","Katori Shi","2111171","","","35.8333","140.6","4"],"289-0403":["JP","289-0403","Kawakami","Chiba Ken","04","Katori Shi","2111171","","","35.8535","140.5401","4"],"289-0404":["JP","289-0404","Koya","Chiba Ken","04","Katori Shi","2111171","","","35.8535","140.5401","4"],"289-0405":["JP","289-0405","Takenochi","Chiba Ken","04","Katori Shi","2111171","","","35.3327","140.1251","1"],"289-0406":["JP","289-0406","Tabe","Chiba Ken","04","Katori Shi","2111171","","","35.8535","140.5401","4"],"289-0407":["JP","289-0407","Nira","Chiba Ken","04","Katori Shi","2111171","","","35.3327","140.1251","1"],"289-0408":["JP","289-0408","Kanno","Chiba Ken","04","Katori Shi","2111171","","","35.8535","140.5401","4"],"289-0411":["JP","289-0411","Fuma","Chiba Ken","04","Katori Shi","2111171","","","35.2248","140.3876","1"],"289-0412":["JP","289-0412","Furuchi","Chiba Ken","04","Katori Shi","2111171","","","35.2248","140.3876","1"],"289-0413":["JP","289-0413","Shidaka","Chiba Ken","04","Katori Shi","2111171","","","35.2248","140.3876","1"],"289-0414":["JP","289-0414","Nagaoka","Chiba Ken","04","Katori Shi","2111171","","","35.8535","140.5401","4"],"289-0421":["JP","289-0421","Hatoyama","Chiba Ken","04","Katori Shi","2111171","","","35.7833","140.5333","1"],"289-0422":["JP","289-0422","Kirizaku","Chiba Ken","04","Katori Shi","2111171","","","35.7833","140.5333","1"],"289-0423":["JP","289-0423","Ogawa","Chiba Ken","04","Katori Shi","2111171","","","35.7833","140.5333","1"],"289-0424":["JP","289-0424","Nissato","Chiba Ken","04","Katori Shi","2111171","","","35.7833","140.5333","1"],"289-0425":["JP","289-0425","Otogari","Chiba Ken","04","Katori Shi","2111171","","","35.7833","140.5333","1"],"289-0426":["JP","289-0426","Yamakura","Chiba Ken","04","Katori Shi","2111171","","","35.7833","140.5333","4"],"289-1600":["JP","289-1600","Ikanikeisaiganaibaai","Chiba Ken","04","Sambu Gun","2111211","Shibayama Machi","12409","35.4524","140.1237","1"],"289-1601":["JP","289-1601","Kayamashinden(Sonota)","Chiba Ken","04","Sambu Gun","2111211","Shibayama Machi","12409","35.4524","140.1237","1"],"289-1602":["JP","289-1602","Hishida(Sonota)","Chiba Ken","04","Sambu Gun","2111211","Shibayama Machi","12409","35.4524","140.1237","1"],"289-1603":["JP","289-1603","Osato(Sonota)","Chiba Ken","04","Sambu Gun","2111211","Shibayama Machi","12409","35.4524","140.1237","1"],"289-1604":["JP","289-1604","Ibitsu","Chiba Ken","04","Sambu Gun","2111211","Shibayama Machi","12409","35.4524","140.1237","1"],"289-1605":["JP","289-1605","Odai","Chiba Ken","04","Sambu Gun","2111211","Shibayama Machi","12409","35.4524","140.1237","1"],"289-1606":["JP","289-1606","Yamada","Chiba Ken","04","Sambu Gun","2111211","Shibayama Machi","12409","35.6571","140.4565","4"],"289-1607":["JP","289-1607","Asakura","Chiba Ken","04","Sambu Gun","2111211","Shibayama Machi","12409","35.4524","140.1237","1"],"289-1608":["JP","289-1608","Iwayama(Sonota)","Chiba Ken","04","Sambu Gun","2111211","Shibayama Machi","12409","35.4524","140.1237","1"],"289-1611":["JP","289-1611","Obaraku","Chiba Ken","04","Sambu Gun","2111211","Shibayama Machi","12409","35.5696","140.1772","1"],"289-1612":["JP","289-1612","Kamifukiire","Chiba Ken","04","Sambu Gun","2111211","Shibayama Machi","12409","35.5696","140.1772","1"],"289-1613":["JP","289-1613","Shimofukiire","Chiba Ken","04","Sambu Gun","2111211","Shibayama Machi","12409","35.5696","140.1772","1"],"289-1614":["JP","289-1614","Miyazaki","Chiba Ken","04","Sambu Gun","2111211","Shibayama Machi","12409","35.6571","140.4565","4"],"289-1615":["JP","289-1615","Sakai","Chiba Ken","04","Sambu Gun","2111211","Shibayama Machi","12409","35.5696","140.1772","1"],"289-1616":["JP","289-1616","Takaya","Chiba Ken","04","Sambu Gun","2111211","Shibayama Machi","12409","35.6571","140.4565","4"],"289-1617":["JP","289-1617","Tonobeta","Chiba Ken","04","Sambu Gun","2111211","Shibayama Machi","12409","35.6571","140.4565","4"],"289-1618":["JP","289-1618","Yamanaka","Chiba Ken","04","Sambu Gun","2111211","Shibayama Machi","12409","35.6571","140.4565","4"],"289-1619":["JP","289-1619","Shibayama","Chiba Ken","04","Sambu Gun","2111211","Shibayama Machi","12409","35.7217","140.41","4"],"289-1621":["JP","289-1621","Makino","Chiba Ken","04","Sambu Gun","2111211","Shibayama Machi","12409","35.5912","140.3657","1"],"289-1622":["JP","289-1622","Homa","Chiba Ken","04","Sambu Gun","2111211","Shibayama Machi","12409","35.5912","140.3657","1"],"289-1623":["JP","289-1623","Takada","Chiba Ken","04","Sambu Gun","2111211","Shibayama Machi","12409","35.6571","140.4565","4"],"289-1624":["JP","289-1624","Koike","Chiba Ken","04","Sambu Gun","2111211","Shibayama Machi","12409","35.6833","140.4167","4"],"289-1625":["JP","289-1625","Niida","Chiba Ken","04","Sambu Gun","2111211","Shibayama Machi","12409","35.5912","140.3657","1"],"289-1626":["JP","289-1626","Niidashinden","Chiba Ken","04","Sambu Gun","2111211","Shibayama Machi","12409","35.5912","140.3657","1"],"289-1700":["JP","289-1700","Ikanikeisaiganaibaai","Chiba Ken","04","Sambu Gun","2111211","Yokoshibahikari Machi","12410","35.4866","140.0952","1"],"289-1701":["JP","289-1701","Sasamoto","Chiba Ken","04","Sambu Gun","2111211","Yokoshibahikari Machi","12410","35.4866","140.0952","1"],"289-1702":["JP","289-1702","Futamata","Chiba Ken","04","Sambu Gun","2111211","Yokoshibahikari Machi","12410","35.6571","140.4565","4"],"289-1703":["JP","289-1703","Hojido","Chiba Ken","04","Sambu Gun","2111211","Yokoshibahikari Machi","12410","35.4866","140.0952","1"],"289-1704":["JP","289-1704","Tomishita","Chiba Ken","04","Sambu Gun","2111211","Yokoshibahikari Machi","12410","35.4866","140.0952","1"],"289-1705":["JP","289-1705","Home","Chiba Ken","04","Sambu Gun","2111211","Yokoshibahikari Machi","12410","35.6571","140.4565","4"],"289-1706":["JP","289-1706","Ichinohara","Chiba Ken","04","Sambu Gun","2111211","Yokoshibahikari Machi","12410","35.4866","140.0952","1"],"289-1707":["JP","289-1707","Arai","Chiba Ken","04","Sambu Gun","2111211","Yokoshibahikari Machi","12410","35.6571","140.4565","4"],"289-1708":["JP","289-1708","Sasamotonegiri","Chiba Ken","04","Sambu Gun","2111211","Yokoshibahikari Machi","12410","35.4866","140.0952","1"],"289-1711":["JP","289-1711","Ogawadai","Chiba Ken","04","Sambu Gun","2111211","Yokoshibahikari Machi","12410","35.2515","139.8594","1"],"289-1712":["JP","289-1712","Dai","Chiba Ken","04","Sambu Gun","2111211","Yokoshibahikari Machi","12410","35.6571","140.4565","4"],"289-1713":["JP","289-1713","Kotabe","Chiba Ken","04","Sambu Gun","2111211","Yokoshibahikari Machi","12410","35.2515","139.8594","1"],"289-1714":["JP","289-1714","Hahako","Chiba Ken","04","Sambu Gun","2111211","Yokoshibahikari Machi","12410","35.2515","139.8594","1"],"289-1715":["JP","289-1715","Shibasaki","Chiba Ken","04","Sambu Gun","2111211","Yokoshibahikari Machi","12410","35.6571","140.4565","4"],"289-1716":["JP","289-1716","Shibasakiminami","Chiba Ken","04","Sambu Gun","2111211","Yokoshibahikari Machi","12410","35.2515","139.8594","1"],"289-1717":["JP","289-1717","Musho","Chiba Ken","04","Sambu Gun","2111211","Yokoshibahikari Machi","12410","35.2515","139.8594","1"],"289-1721":["JP","289-1721","Yanaka","Chiba Ken","04","Sambu Gun","2111211","Yokoshibahikari Machi","12410","35.6571","140.4565","4"],"289-1722":["JP","289-1722","Mejino","Chiba Ken","04","Sambu Gun","2111211","Yokoshibahikari Machi","12410","35.5617","140.3504","1"],"289-1723":["JP","289-1723","Kambara","Chiba Ken","04","Sambu Gun","2111211","Yokoshibahikari Machi","12410","35.5617","140.3504","1"],"289-1724":["JP","289-1724","Harakata","Chiba Ken","04","Sambu Gun","2111211","Yokoshibahikari Machi","12410","35.5617","140.3504","1"],"289-1725":["JP","289-1725","Odare","Chiba Ken","04","Sambu Gun","2111211","Yokoshibahikari Machi","12410","35.5617","140.3504","1"],"289-1726":["JP","289-1726","Kido","Chiba Ken","04","Sambu Gun","2111211","Yokoshibahikari Machi","12410","35.6333","140.5333","4"],"289-1727":["JP","289-1727","Miyagawa","Chiba Ken","04","Sambu Gun","2111211","Yokoshibahikari Machi","12410","35.65","140.5","4"],"289-1731":["JP","289-1731","Kokawa","Chiba Ken","04","Sambu Gun","2111211","Yokoshibahikari Machi","12410","35.4692","140.3595","1"],"289-1732":["JP","289-1732","Yokoshiba","Chiba Ken","04","Sambu Gun","2111211","Yokoshibahikari Machi","12410","35.65","140.4833","4"],"289-1733":["JP","289-1733","Kuriyama","Chiba Ken","04","Sambu Gun","2111211","Yokoshibahikari Machi","12410","35.6571","140.4565","4"],"289-1734":["JP","289-1734","Kitashimizu","Chiba Ken","04","Sambu Gun","2111211","Yokoshibahikari Machi","12410","35.4692","140.3595","1"],"289-1735":["JP","289-1735","Yakata","Chiba Ken","04","Sambu Gun","2111211","Yokoshibahikari Machi","12410","35.4692","140.3595","1"],"289-1736":["JP","289-1736","Niijima","Chiba Ken","04","Sambu Gun","2111211","Yokoshibahikari Machi","12410","35.4692","140.3595","1"],"289-1737":["JP","289-1737","Torihamishimo","Chiba Ken","04","Sambu Gun","2111211","Yokoshibahikari Machi","12410","35.4692","140.3595","1"],"289-1738":["JP","289-1738","Torihamikami","Chiba Ken","04","Sambu Gun","2111211","Yokoshibahikari Machi","12410","35.4692","140.3595","1"],"289-1739":["JP","289-1739","Torihamishinden","Chiba Ken","04","Sambu Gun","2111211","Yokoshibahikari Machi","12410","35.4692","140.3595","1"],"289-1741":["JP","289-1741","Nakadai","Chiba Ken","04","Sambu Gun","2111211","Yokoshibahikari Machi","12410","35.6571","140.4565","4"],"289-1742":["JP","289-1742","Ushikuma","Chiba Ken","04","Sambu Gun","2111211","Yokoshibahikari Machi","12410","35.0547","139.9544","1"],"289-1743":["JP","289-1743","Yatsudai","Chiba Ken","04","Sambu Gun","2111211","Yokoshibahikari Machi","12410","35.0547","139.9544","1"],"289-1744":["JP","289-1744","Kidodai","Chiba Ken","04","Sambu Gun","2111211","Yokoshibahikari Machi","12410","35.0547","139.9544","1"],"289-1745":["JP","289-1745","Onzumi","Chiba Ken","04","Sambu Gun","2111211","Yokoshibahikari Machi","12410","35.0547","139.9544","1"],"289-1746":["JP","289-1746","Terakata","Chiba Ken","04","Sambu Gun","2111211","Yokoshibahikari Machi","12410","35.0547","139.9544","1"],"289-1747":["JP","289-1747","Soneai","Chiba Ken","04","Sambu Gun","2111211","Yokoshibahikari Machi","12410","35.0547","139.9544","1"],"289-1748":["JP","289-1748","Oki","Chiba Ken","04","Sambu Gun","2111211","Yokoshibahikari Machi","12410","35.0547","139.9544","1"],"289-1749":["JP","289-1749","Ryogokushinden","Chiba Ken","04","Sambu Gun","2111211","Yokoshibahikari Machi","12410","35.0547","139.9544","1"],"289-1751":["JP","289-1751","Nagayamadai","Chiba Ken","04","Sambu Gun","2111211","Yokoshibahikari Machi","12410","34.9758","139.7738","1"],"289-1752":["JP","289-1752","Ubayama","Chiba Ken","04","Sambu Gun","2111211","Yokoshibahikari Machi","12410","34.9758","139.7738","1"],"289-1753":["JP","289-1753","Toritate","Chiba Ken","04","Sambu Gun","2111211","Yokoshibahikari Machi","12410","34.9758","139.7738","1"],"289-1754":["JP","289-1754","Sakata","Chiba Ken","04","Sambu Gun","2111211","Yokoshibahikari Machi","12410","35.6571","140.4565","4"],"289-1755":["JP","289-1755","Sakataike","Chiba Ken","04","Sambu Gun","2111211","Yokoshibahikari Machi","12410","34.9758","139.7738","1"],"289-1756":["JP","289-1756","Nagakura","Chiba Ken","04","Sambu Gun","2111211","Yokoshibahikari Machi","12410","34.9758","139.7738","1"],"289-1757":["JP","289-1757","Toyama","Chiba Ken","04","Sambu Gun","2111211","Yokoshibahikari Machi","12410","34.9758","139.7738","1"],"289-0101":["JP","289-0101","Kobuke","Chiba Ken","04","Narita Shi","2111683","","","35.3104","140.3023","1"],"289-0102":["JP","289-0102","Nomagome","Chiba Ken","04","Narita Shi","2111683","","","35.3104","140.3023","1"],"289-0103":["JP","289-0103","Taka","Chiba Ken","04","Narita Shi","2111683","","","35.3104","140.3023","1"],"289-0104":["JP","289-0104","Tobu","Chiba Ken","04","Narita Shi","2111683","","","35.3104","140.3023","1"],"289-0105":["JP","289-0105","Nakazato","Chiba Ken","04","Narita Shi","2111683","","","35.8154","140.3575","4"],"289-0106":["JP","289-0106","Ono","Chiba Ken","04","Narita Shi","2111683","","","35.3104","140.3023","1"],"289-0107":["JP","289-0107","Saruyama","Chiba Ken","04","Narita Shi","2111683","","","35.3104","140.3023","1"],"289-0108":["JP","289-0108","Takaoka","Chiba Ken","04","Narita Shi","2111683","","","35.3104","140.3023","1"],"289-0109":["JP","289-0109","Owada","Chiba Ken","04","Narita Shi","2111683","","","35.8154","140.3575","4"],"289-0111":["JP","289-0111","Nagi","Chiba Ken","04","Narita Shi","2111683","","","35.8154","140.3575","4"],"289-0112":["JP","289-0112","Aoyama","Chiba Ken","04","Narita Shi","2111683","","","35.1575","140.2297","1"],"289-0113":["JP","289-0113","Kuramizu","Chiba Ken","04","Narita Shi","2111683","","","35.1575","140.2297","1"],"289-0114":["JP","289-0114","Narui","Chiba Ken","04","Narita Shi","2111683","","","35.1575","140.2297","1"],"289-0115":["JP","289-0115","Jizoharashinden","Chiba Ken","04","Narita Shi","2111683","","","35.1575","140.2297","1"],"289-0116":["JP","289-0116","Nagoya","Chiba Ken","04","Narita Shi","2111683","","","35.1575","140.2297","1"],"289-0117":["JP","289-0117","Nanasawa","Chiba Ken","04","Narita Shi","2111683","","","35.1575","140.2297","1"],"289-0121":["JP","289-0121","Osuge","Chiba Ken","04","Narita Shi","2111683","","","35.6008","140.1726","1"],"289-0122":["JP","289-0122","Takakura","Chiba Ken","04","Narita Shi","2111683","","","35.8154","140.3575","4"],"289-0123":["JP","289-0123","Yotsuya","Chiba Ken","04","Narita Shi","2111683","","","35.6008","140.1726","1"],"289-0124":["JP","289-0124","Nishiosuka","Chiba Ken","04","Narita Shi","2111683","","","35.6008","140.1726","1"],"289-0125":["JP","289-0125","Namegawa","Chiba Ken","04","Narita Shi","2111683","","","35.8667","140.35","4"],"289-0126":["JP","289-0126","Shinkawa","Chiba Ken","04","Narita Shi","2111683","","","35.6008","140.1726","1"],"289-0100":["JP","289-0100","Ikanikeisaiganaibaai","Chiba Ken","04","Katori Gun","2112318","Kozaki Machi","12342","35.3104","140.3023","1"],"289-0201":["JP","289-0201","Koya","Chiba Ken","04","Katori Gun","2112318","Kozaki Machi","12342","35.7943","140.5289","4"],"289-0202":["JP","289-0202","Kori","Chiba Ken","04","Katori Gun","2112318","Kozaki Machi","12342","35.7943","140.5289","4"],"289-0203":["JP","289-0203","Onuki","Chiba Ken","04","Katori Gun","2112318","Kozaki Machi","12342","35.2965","139.9058","1"],"289-0204":["JP","289-0204","Shikinoka","Chiba Ken","04","Katori Gun","2112318","Kozaki Machi","12342","35.2965","139.9058","1"],"289-0205":["JP","289-0205","Ima","Chiba Ken","04","Katori Gun","2112318","Kozaki Machi","12342","35.2965","139.9058","1"],"289-0211":["JP","289-0211","Tachino","Chiba Ken","04","Katori Gun","2112318","Kozaki Machi","12342","35.8227","139.9867","1"],"289-0212":["JP","289-0212","Takeda","Chiba Ken","04","Katori Gun","2112318","Kozaki Machi","12342","35.8227","139.9867","1"],"289-0213":["JP","289-0213","Shin","Chiba Ken","04","Katori Gun","2112318","Kozaki Machi","12342","35.8227","139.9867","1"],"289-0214":["JP","289-0214","Kenari","Chiba Ken","04","Katori Gun","2112318","Kozaki Machi","12342","35.8227","139.9867","1"],"289-0215":["JP","289-0215","Kohara","Chiba Ken","04","Katori Gun","2112318","Kozaki Machi","12342","35.8227","139.9867","1"],"289-0216":["JP","289-0216","Uebo","Chiba Ken","04","Katori Gun","2112318","Kozaki Machi","12342","35.8227","139.9867","1"],"289-0217":["JP","289-0217","Fujinodai","Chiba Ken","04","Katori Gun","2112318","Kozaki Machi","12342","35.7943","140.5289","4"],"289-0221":["JP","289-0221","Kozakihonshuku","Chiba Ken","04","Katori Gun","2112318","Kozaki Machi","12342","35.3777","140.0439","1"],"289-0222":["JP","289-0222","Namiki","Chiba Ken","04","Katori Gun","2112318","Kozaki Machi","12342","35.7943","140.5289","4"],"289-0223":["JP","289-0223","Komatsu","Chiba Ken","04","Katori Gun","2112318","Kozaki Machi","12342","35.3777","140.0439","1"],"289-0224":["JP","289-0224","Matsuzaki","Chiba Ken","04","Katori Gun","2112318","Kozaki Machi","12342","35.7943","140.5289","4"],"289-0225":["JP","289-0225","Jusammado","Chiba Ken","04","Katori Gun","2112318","Kozaki Machi","12342","35.3777","140.0439","1"],"289-0226":["JP","289-0226","Kozakishinshuku","Chiba Ken","04","Katori Gun","2112318","Kozaki Machi","12342","35.3777","140.0439","1"],"289-0600":["JP","289-0600","Ikanikeisaiganaibaai","Chiba Ken","04","Katori Gun","2112318","Tonosho Machi","12349","35.3122","140.1095","1"],"289-0601":["JP","289-0601","Sasagawai","Chiba Ken","04","Katori Gun","2112318","Tonosho Machi","12349","35.3122","140.1095","1"],"289-0602":["JP","289-0602","Sasagawaro","Chiba Ken","04","Katori Gun","2112318","Tonosho Machi","12349","35.3122","140.1095","1"],"289-0611":["JP","289-0611","Niijuku","Chiba Ken","04","Katori Gun","2112318","Tonosho Machi","12349","35.7943","140.5289","4"],"289-0612":["JP","289-0612","Ishide","Chiba Ken","04","Katori Gun","2112318","Tonosho Machi","12349","35.2421","140.1163","1"],"289-0613":["JP","289-0613","Higashiimaizumi","Chiba Ken","04","Katori Gun","2112318","Tonosho Machi","12349","35.2421","140.1163","1"],"289-0614":["JP","289-0614","Miyamoto","Chiba Ken","04","Katori Gun","2112318","Tonosho Machi","12349","35.7943","140.5289","4"],"289-0615":["JP","289-0615","Oma","Chiba Ken","04","Katori Gun","2112318","Tonosho Machi","12349","35.2421","140.1163","1"],"289-0616":["JP","289-0616","Takabe","Chiba Ken","04","Katori Gun","2112318","Tonosho Machi","12349","35.7943","140.5289","4"],"289-0617":["JP","289-0617","Habakari","Chiba Ken","04","Katori Gun","2112318","Tonosho Machi","12349","35.2421","140.1163","1"],"289-0618":["JP","289-0618","Yazu","Chiba Ken","04","Katori Gun","2112318","Tonosho Machi","12349","35.7943","140.5289","4"],"289-0619":["JP","289-0619","Imagori","Chiba Ken","04","Katori Gun","2112318","Tonosho Machi","12349","35.2421","140.1163","1"],"289-0621":["JP","289-0621","Otomo","Chiba Ken","04","Katori Gun","2112318","Tonosho Machi","12349","35.3245","140.3677","1"],"289-0622":["JP","289-0622","Oza","Chiba Ken","04","Katori Gun","2112318","Tonosho Machi","12349","35.3245","140.3677","1"],"289-0623":["JP","289-0623","Miyanodai","Chiba Ken","04","Katori Gun","2112318","Tonosho Machi","12349","35.7943","140.5289","4"],"289-0624":["JP","289-0624","Kominami","Chiba Ken","04","Katori Gun","2112318","Tonosho Machi","12349","35.3245","140.3677","1"],"289-0625":["JP","289-0625","Natsume","Chiba Ken","04","Katori Gun","2112318","Tonosho Machi","12349","35.3245","140.3677","1"],"289-0626":["JP","289-0626","Yaebo","Chiba Ken","04","Katori Gun","2112318","Tonosho Machi","12349","35.3245","140.3677","1"],"289-0627":["JP","289-0627","Awano","Chiba Ken","04","Katori Gun","2112318","Tonosho Machi","12349","35.3245","140.3677","1"],"289-0631":["JP","289-0631","Hirayama","Chiba Ken","04","Katori Gun","2112318","Tonosho Machi","12349","35.7943","140.5289","4"],"289-0632":["JP","289-0632","Kubonoya","Chiba Ken","04","Katori Gun","2112318","Tonosho Machi","12349","35.3792","140.0381","1"],"289-0633":["JP","289-0633","Okubo","Chiba Ken","04","Katori Gun","2112318","Tonosho Machi","12349","35.7943","140.5289","4"],"289-0634":["JP","289-0634","Funado","Chiba Ken","04","Katori Gun","2112318","Tonosho Machi","12349","35.7943","140.5289","4"],"289-0635":["JP","289-0635","Kanda","Chiba Ken","04","Katori Gun","2112318","Tonosho Machi","12349","35.7943","140.5289","4"],"289-0636":["JP","289-0636","Towada","Chiba Ken","04","Katori Gun","2112318","Tonosho Machi","12349","35.3792","140.0381","1"],"289-0637":["JP","289-0637","Kogaino","Chiba Ken","04","Katori Gun","2112318","Tonosho Machi","12349","35.3792","140.0381","1"],"289-2200":["JP","289-2200","Ikanikeisaiganaibaai","Chiba Ken","04","Katori Gun","2112318","Tako Machi","12347","35.4397","140.319","1"],"289-2231":["JP","289-2231","Iizasa","Chiba Ken","04","Katori Gun","2112318","Tako Machi","12347","35.3868","140.2727","1"],"289-2232":["JP","289-2232","Kita","Chiba Ken","04","Katori Gun","2112318","Tako Machi","12347","35.7943","140.5289","4"],"289-2233":["JP","289-2233","Hayashi","Chiba Ken","04","Katori Gun","2112318","Tako Machi","12347","35.7943","140.5289","4"],"289-2234":["JP","289-2234","Gotanda","Chiba Ken","04","Katori Gun","2112318","Tako Machi","12347","35.7943","140.5289","4"],"289-2235":["JP","289-2235","Magura","Chiba Ken","04","Katori Gun","2112318","Tako Machi","12347","35.3868","140.2727","1"],"289-2236":["JP","289-2236","Hitokuwada(Sonota)","Chiba Ken","04","Katori Gun","2112318","Tako Machi","12347","35.3868","140.2727","1"],"289-2241":["JP","289-2241","Tako","Chiba Ken","04","Katori Gun","2112318","Tako Machi","12347","35.7333","140.4667","4"],"289-2242":["JP","289-2242","Somei","Chiba Ken","04","Katori Gun","2112318","Tako Machi","12347","35.5192","140.3885","1"],"289-2243":["JP","289-2243","Shima","Chiba Ken","04","Katori Gun","2112318","Tako Machi","12347","35.7943","140.5289","4"],"289-2244":["JP","289-2244","Funakoshi","Chiba Ken","04","Katori Gun","2112318","Tako Machi","12347","35.5192","140.3885","1"],"289-2245":["JP","289-2245","Ushino","Chiba Ken","04","Katori Gun","2112318","Tako Machi","12347","35.5192","140.3885","1"],"289-2246":["JP","289-2246","Chida","Chiba Ken","04","Katori Gun","2112318","Tako Machi","12347","35.5192","140.3885","1"],"289-2247":["JP","289-2247","Mito","Chiba Ken","04","Katori Gun","2112318","Tako Machi","12347","35.5192","140.3885","1"],"289-2251":["JP","289-2251","Kitanaka","Chiba Ken","04","Katori Gun","2112318","Tako Machi","12347","35.4397","140.319","1"],"289-2252":["JP","289-2252","Minamiwada","Chiba Ken","04","Katori Gun","2112318","Tako Machi","12347","35.4397","140.319","1"],"289-2253":["JP","289-2253","Minamikariate","Chiba Ken","04","Katori Gun","2112318","Tako Machi","12347","35.4397","140.319","1"],"289-2254":["JP","289-2254","Toki","Chiba Ken","04","Katori Gun","2112318","Tako Machi","12347","35.4397","140.319","1"],"289-2255":["JP","289-2255","Minaminamiki","Chiba Ken","04","Katori Gun","2112318","Tako Machi","12347","35.4397","140.319","1"],"289-2256":["JP","289-2256","Nakamurashinden","Chiba Ken","04","Katori Gun","2112318","Tako Machi","12347","35.4397","140.319","1"],"289-2257":["JP","289-2257","Minaminaka","Chiba Ken","04","Katori Gun","2112318","Tako Machi","12347","35.4397","140.319","1"],"289-2301":["JP","289-2301","Idenuma","Chiba Ken","04","Katori Gun","2112318","Tako Machi","12347","35.2637","140.0927","1"],"289-2302":["JP","289-2302","Hinoki","Chiba Ken","04","Katori Gun","2112318","Tako Machi","12347","35.2637","140.0927","1"],"289-2303":["JP","289-2303","Okado","Chiba Ken","04","Katori Gun","2112318","Tako Machi","12347","35.2637","140.0927","1"],"289-2304":["JP","289-2304","Takatsuhara","Chiba Ken","04","Katori Gun","2112318","Tako Machi","12347","35.2637","140.0927","1"],"289-2305":["JP","289-2305","Otaka","Chiba Ken","04","Katori Gun","2112318","Tako Machi","12347","35.2637","140.0927","1"],"289-2306":["JP","289-2306","Toyomi","Chiba Ken","04","Katori Gun","2112318","Tako Machi","12347","35.2637","140.0927","1"],"289-2311":["JP","289-2311","Motomikura","Chiba Ken","04","Katori Gun","2112318","Tako Machi","12347","35.2637","140.0927","1"],"289-2312":["JP","289-2312","Sakumikura","Chiba Ken","04","Katori Gun","2112318","Tako Machi","12347","35.2637","140.0927","1"],"289-2313":["JP","289-2313","Tsugiura","Chiba Ken","04","Katori Gun","2112318","Tako Machi","12347","35.2637","140.0927","1"],"289-2314":["JP","289-2314","Nishifuruchi","Chiba Ken","04","Katori Gun","2112318","Tako Machi","12347","35.2637","140.0927","1"],"289-2315":["JP","289-2315","Goshodai","Chiba Ken","04","Katori Gun","2112318","Tako Machi","12347","35.2637","140.0927","1"],"289-2316":["JP","289-2316","Terasaku","Chiba Ken","04","Katori Gun","2112318","Tako Machi","12347","35.2637","140.0927","1"],"289-2317":["JP","289-2317","Idoyama","Chiba Ken","04","Katori Gun","2112318","Tako Machi","12347","35.2637","140.0927","1"],"289-2321":["JP","289-2321","Higashimatsusaki","Chiba Ken","04","Katori Gun","2112318","Tako Machi","12347","35.2637","140.0927","1"],"289-2322":["JP","289-2322","Saka","Chiba Ken","04","Katori Gun","2112318","Tako Machi","12347","35.2637","140.0927","1"],"289-2323":["JP","289-2323","Hoda","Chiba Ken","04","Katori Gun","2112318","Tako Machi","12347","35.7943","140.5289","4"],"289-2324":["JP","289-2324","Kawashima","Chiba Ken","04","Katori Gun","2112318","Tako Machi","12347","35.7943","140.5289","4"],"289-2325":["JP","289-2325","Minamitamatsukuri","Chiba Ken","04","Katori Gun","2112318","Tako Machi","12347","35.2637","140.0927","1"],"289-0501":["JP","289-0501","Seiwaotsu","Chiba Ken","04","Asahi Shi","2113074","","","35.5233","140.2069","1"],"289-0502":["JP","289-0502","Nagabe","Chiba Ken","04","Asahi Shi","2113074","","","35.5233","140.2069","1"],"289-0503":["JP","289-0503","Mizowara","Chiba Ken","04","Asahi Shi","2113074","","","35.5233","140.2069","1"],"289-0504":["JP","289-0504","Sakurai","Chiba Ken","04","Asahi Shi","2113074","","","35.7342","140.6559","4"],"289-0505":["JP","289-0505","Manzai","Chiba Ken","04","Asahi Shi","2113074","","","35.7667","140.65","4"],"289-0506":["JP","289-0506","Sakuradai","Chiba Ken","04","Asahi Shi","2113074","","","35.7342","140.6559","4"],"289-0507":["JP","289-0507","Seiwako","Chiba Ken","04","Asahi Shi","2113074","","","35.5233","140.2069","1"],"289-0511":["JP","289-0511","Kaburaki","Chiba Ken","04","Asahi Shi","2113074","","","35.75","140.5833","4"],"289-0512":["JP","289-0512","Minamihorinochi","Chiba Ken","04","Asahi Shi","2113074","","","35.6791","140.2815","1"],"289-0513":["JP","289-0513","Funado","Chiba Ken","04","Asahi Shi","2113074","","","35.7342","140.6559","4"],"289-0514":["JP","289-0514","Sekido","Chiba Ken","04","Asahi Shi","2113074","","","35.7342","140.6559","4"],"289-0515":["JP","289-0515","Irino","Chiba Ken","04","Asahi Shi","2113074","","","35.6791","140.2815","1"],"289-0516":["JP","289-0516","Yonegome","Chiba Ken","04","Asahi Shi","2113074","","","35.6791","140.2815","1"],"289-0517":["JP","289-0517","Manriki","Chiba Ken","04","Asahi Shi","2113074","","","35.6791","140.2815","1"],"289-0518":["JP","289-0518","Akita","Chiba Ken","04","Asahi Shi","2113074","","","35.6791","140.2815","1"],"289-2500":["JP","289-2500","Ikanikeisaiganaibaai","Chiba Ken","04","Asahi Shi","2113074","","","35.1874","140.3579","1"],"289-2501":["JP","289-2501","Shimmachi","Chiba Ken","04","Asahi Shi","2113074","","","35.7342","140.6559","4"],"289-2502":["JP","289-2502","Kotoda(Sonota)","Chiba Ken","04","Asahi Shi","2113074","","","35.1874","140.3579","1"],"289-2503":["JP","289-2503","Egasaki(Sonota)","Chiba Ken","04","Asahi Shi","2113074","","","35.1874","140.3579","1"],"289-2504":["JP","289-2504","Ni","Chiba Ken","04","Asahi Shi","2113074","","","35.1874","140.3579","1"],"289-2505":["JP","289-2505","Kamakazu","Chiba Ken","04","Asahi Shi","2113074","","","35.1874","140.3579","1"],"289-2511":["JP","289-2511","I","Chiba Ken","04","Asahi Shi","2113074","","","35.3561","140.1961","1"],"289-2512":["JP","289-2512","Higashiashiarai","Chiba Ken","04","Asahi Shi","2113074","","","35.3561","140.1961","1"],"289-2513":["JP","289-2513","Nonaka","Chiba Ken","04","Asahi Shi","2113074","","","35.3561","140.1961","1"],"289-2514":["JP","289-2514","Shiinauchi","Chiba Ken","04","Asahi Shi","2113074","","","35.3561","140.1961","1"],"289-2515":["JP","289-2515","Nishiashiarai","Chiba Ken","04","Asahi Shi","2113074","","","35.3561","140.1961","1"],"289-2516":["JP","289-2516","Ro","Chiba Ken","04","Asahi Shi","2113074","","","35.3561","140.1961","1"],"289-2521":["JP","289-2521","Ha","Chiba Ken","04","Asahi Shi","2113074","","","35.7342","140.6559","4"],"289-2522":["JP","289-2522","Ashikawa","Chiba Ken","04","Asahi Shi","2113074","","","35.5167","140.0833","1"],"289-2523":["JP","289-2523","Nakayari","Chiba Ken","04","Asahi Shi","2113074","","","35.5167","140.0833","1"],"289-2524":["JP","289-2524","Jinguji","Chiba Ken","04","Asahi Shi","2113074","","","35.5167","140.0833","1"],"289-2525":["JP","289-2525","Nittama","Chiba Ken","04","Asahi Shi","2113074","","","35.5167","140.0833","1"],"289-2531":["JP","289-2531","Idono","Chiba Ken","04","Asahi Shi","2113074","","","35.3642","140.147","1"],"289-2532":["JP","289-2532","Komagome","Chiba Ken","04","Asahi Shi","2113074","","","35.7342","140.6559","4"],"289-2533":["JP","289-2533","Otsukahara","Chiba Ken","04","Asahi Shi","2113074","","","35.3642","140.147","1"],"289-2534":["JP","289-2534","Izumikawa","Chiba Ken","04","Asahi Shi","2113074","","","35.3642","140.147","1"],"289-2535":["JP","289-2535","Kawaguchi","Chiba Ken","04","Asahi Shi","2113074","","","35.3642","140.147","1"],"289-2601":["JP","289-2601","Matsugaya","Chiba Ken","04","Asahi Shi","2113074","","","35.3535","140.3394","1"],"289-2602":["JP","289-2602","Iwai","Chiba Ken","04","Asahi Shi","2113074","","","35.7342","140.6559","4"],"289-2603":["JP","289-2603","Omade","Chiba Ken","04","Asahi Shi","2113074","","","35.3535","140.3394","1"],"289-2604":["JP","289-2604","Takaoi","Chiba Ken","04","Asahi Shi","2113074","","","35.3535","140.3394","1"],"289-2605":["JP","289-2605","3598-3614-Banchi)","Chiba Ken","04","Asahi Shi","2113074","","","35.3535","140.3394","1"],"289-2606":["JP","289-2606","Kiyotaki","Chiba Ken","04","Asahi Shi","2113074","","","35.3535","140.3394","1"],"289-2607":["JP","289-2607","Ikuyo","Chiba Ken","04","Asahi Shi","2113074","","","35.3535","140.3394","1"],"289-2611":["JP","289-2611","Kurahashi","Chiba Ken","04","Asahi Shi","2113074","","","35.46","140.2905","1"],"289-2612":["JP","289-2612","Hebisono","Chiba Ken","04","Asahi Shi","2113074","","","35.46","140.2905","1"],"289-2613":["JP","289-2613","Ushirogusa","Chiba Ken","04","Asahi Shi","2113074","","","35.46","140.2905","1"],"289-2614":["JP","289-2614","Egasaki(12-22.127-140.1709.1723-3.","Chiba Ken","04","Asahi Shi","2113074","","","35.46","140.2905","1"],"289-2615":["JP","289-2615","Nagao","Chiba Ken","04","Asahi Shi","2113074","","","35.7342","140.6559","4"],"289-2616":["JP","289-2616","Mihiro","Chiba Ken","04","Asahi Shi","2113074","","","35.46","140.2905","1"],"289-2701":["JP","289-2701","Mujinano","Chiba Ken","04","Asahi Shi","2113074","","","35.3722","140.241","1"],"289-2702":["JP","289-2702","Hanawa","Chiba Ken","04","Asahi Shi","2113074","","","35.7342","140.6559","4"],"289-2703":["JP","289-2703","Yagi","Chiba Ken","04","Asahi Shi","2113074","","","35.7342","140.6559","4"],"289-2704":["JP","289-2704","Kaminagai","Chiba Ken","04","Asahi Shi","2113074","","","35.3722","140.241","1"],"289-2705":["JP","289-2705","Iioka","Chiba Ken","04","Asahi Shi","2113074","","","35.7","140.7167","4"],"289-2706":["JP","289-2706","Shimonagai","Chiba Ken","04","Asahi Shi","2113074","","","35.3722","140.241","1"],"289-2707":["JP","289-2707","Gyoji","Chiba Ken","04","Asahi Shi","2113074","","","35.3722","140.241","1"],"289-2708":["JP","289-2708","Hiramatsu","Chiba Ken","04","Asahi Shi","2113074","","","35.7342","140.6559","4"],"289-2711":["JP","289-2711","Iwasaki","Chiba Ken","04","Asahi Shi","2113074","","","35.7342","140.6559","4"],"289-2712":["JP","289-2712","Yokone","Chiba Ken","04","Asahi Shi","2113074","","","35.7342","140.6559","4"],"289-2713":["JP","289-2713","Hagizono","Chiba Ken","04","Asahi Shi","2113074","","","35.2468","139.984","1"],"289-2714":["JP","289-2714","Sangawa","Chiba Ken","04","Asahi Shi","2113074","","","35.2468","139.984","1"],"289-2715":["JP","289-2715","Gondanumashinden","Chiba Ken","04","Asahi Shi","2113074","","","35.2468","139.984","1"],"289-2100":["JP","289-2100","Ikanikeisaiganaibaai","Chiba Ken","04","Sosa Shi","7465522","","","35.5213","140.4319","1"],"289-2101":["JP","289-2101","Harumi","Chiba Ken","04","Sosa Shi","7465522","","","35.5213","140.4319","1"],"289-2102":["JP","289-2102","Tsubaki","Chiba Ken","04","Sosa Shi","7465522","","","35.7167","140.5667","4"],"289-2103":["JP","289-2103","Miyamoto","Chiba Ken","04","Sosa Shi","7465522","","","35.6998","140.5538","4"],"289-2104":["JP","289-2104","Oio","Chiba Ken","04","Sosa Shi","7465522","","","35.5213","140.4319","1"],"289-2105":["JP","289-2105","Yamakuwa","Chiba Ken","04","Sosa Shi","7465522","","","35.5213","140.4319","1"],"289-2106":["JP","289-2106","Iizuka","Chiba Ken","04","Sosa Shi","7465522","","","35.6998","140.5538","4"],"289-2107":["JP","289-2107","Yonemochi","Chiba Ken","04","Sosa Shi","7465522","","","35.5213","140.4319","1"],"289-2108":["JP","289-2108","Odera","Chiba Ken","04","Sosa Shi","7465522","","","35.75","140.5667","4"],"289-2111":["JP","289-2111","Kawamukai","Chiba Ken","04","Sosa Shi","7465522","","","35.6998","140.5538","4"],"289-2112":["JP","289-2112","Ogino","Chiba Ken","04","Sosa Shi","7465522","","","35.3697","140.2995","1"],"289-2113":["JP","289-2113","Hiragi","Chiba Ken","04","Sosa Shi","7465522","","","35.3697","140.2995","1"],"289-2114":["JP","289-2114","Joyanaka","Chiba Ken","04","Sosa Shi","7465522","","","35.3697","140.2995","1"],"289-2115":["JP","289-2115","Higashiya","Chiba Ken","04","Sosa Shi","7465522","","","35.3697","140.2995","1"],"289-2121":["JP","289-2121","Higashikozasa","Chiba Ken","04","Sosa Shi","7465522","","","35.4095","140.1549","1"],"289-2122":["JP","289-2122","Yoshizaki","Chiba Ken","04","Sosa Shi","7465522","","","35.4095","140.1549","1"],"289-2123":["JP","289-2123","Nagaya","Chiba Ken","04","Sosa Shi","7465522","","","35.6998","140.5538","4"],"289-2124":["JP","289-2124","Nobuto","Chiba Ken","04","Sosa Shi","7465522","","","35.6998","140.5538","4"],"289-2125":["JP","289-2125","Nishikozasa","Chiba Ken","04","Sosa Shi","7465522","","","35.4095","140.1549","1"],"289-2131":["JP","289-2131","Midoridaira","Chiba Ken","04","Sosa Shi","7465522","","","35.2026","140.1729","1"],"289-2132":["JP","289-2132","Taka","Chiba Ken","04","Sosa Shi","7465522","","","35.2026","140.1729","1"],"289-2133":["JP","289-2133","Kabuzato","Chiba Ken","04","Sosa Shi","7465522","","","35.2026","140.1729","1"],"289-2134":["JP","289-2134","Yokosuka","Chiba Ken","04","Sosa Shi","7465522","","","35.6998","140.5538","4"],"289-2135":["JP","289-2135","Koya","Chiba Ken","04","Sosa Shi","7465522","","","35.6998","140.5538","4"],"289-2136":["JP","289-2136","Tokizone","Chiba Ken","04","Sosa Shi","7465522","","","35.2026","140.1729","1"],"289-2141":["JP","289-2141","Yokaichiba Ha","Chiba Ken","04","Sosa Shi","7465522","","","35.922","139.8944","1"],"289-2142":["JP","289-2142","Yokaichiba Ni","Chiba Ken","04","Sosa Shi","7465522","","","35.922","139.8944","1"],"289-2143":["JP","289-2143","Yokaichiba Ro","Chiba Ken","04","Sosa Shi","7465522","","","35.922","139.8944","1"],"289-2144":["JP","289-2144","Yokaichiba I","Chiba Ken","04","Sosa Shi","7465522","","","35.922","139.8944","1"],"289-2145":["JP","289-2145","Wakashiocho","Chiba Ken","04","Sosa Shi","7465522","","","35.922","139.8944","1"],"289-2146":["JP","289-2146","Yokaichiba Ho","Chiba Ken","04","Sosa Shi","7465522","","","35.922","139.8944","1"],"289-2147":["JP","289-2147","Iigura","Chiba Ken","04","Sosa Shi","7465522","","","35.922","139.8944","1"],"289-2148":["JP","289-2148","Iiguradai","Chiba Ken","04","Sosa Shi","7465522","","","35.922","139.8944","1"],"289-2149":["JP","289-2149","Kaizuka","Chiba Ken","04","Sosa Shi","7465522","","","35.6998","140.5538","4"],"289-2151":["JP","289-2151","Oura","Chiba Ken","04","Sosa Shi","7465522","","","35.2049","140.0652","1"],"289-2152":["JP","289-2152","Matsuyama","Chiba Ken","04","Sosa Shi","7465522","","","35.6998","140.5538","4"],"289-2153":["JP","289-2153","Nakadai","Chiba Ken","04","Sosa Shi","7465522","","","35.6998","140.5538","4"],"289-2154":["JP","289-2154","Tomioka","Chiba Ken","04","Sosa Shi","7465522","","","35.2049","140.0652","1"],"289-2155":["JP","289-2155","Yappe","Chiba Ken","04","Sosa Shi","7465522","","","35.2049","140.0652","1"],"289-2156":["JP","289-2156","Nagaoka","Chiba Ken","04","Sosa Shi","7465522","","","35.6998","140.5538","4"],"289-2157":["JP","289-2157","Horinochi","Chiba Ken","04","Sosa Shi","7465522","","","35.2049","140.0652","1"],"289-2161":["JP","289-2161","Iriyamazaki","Chiba Ken","04","Sosa Shi","7465522","","","35.5065","140.1765","1"],"289-2162":["JP","289-2162","Minamiyamazaki","Chiba Ken","04","Sosa Shi","7465522","","","35.5065","140.1765","1"],"289-2163":["JP","289-2163","Minamikanzaki","Chiba Ken","04","Sosa Shi","7465522","","","35.5065","140.1765","1"],"289-2164":["JP","289-2164","Kizumi","Chiba Ken","04","Sosa Shi","7465522","","","35.5065","140.1765","1"],"289-2165":["JP","289-2165","Takubo","Chiba Ken","04","Sosa Shi","7465522","","","35.5065","140.1765","1"],"289-2166":["JP","289-2166","Shimura","Chiba Ken","04","Sosa Shi","7465522","","","35.5065","140.1765","1"],"289-2167":["JP","289-2167","Kamezaki","Chiba Ken","04","Sosa Shi","7465522","","","35.6998","140.5538","4"],"289-2168":["JP","289-2168","Hisakata","Chiba Ken","04","Sosa Shi","7465522","","","35.5065","140.1765","1"],"289-2169":["JP","289-2169","Yoshida","Chiba Ken","04","Sosa Shi","7465522","","","35.7167","140.5","4"],"289-2171":["JP","289-2171","Uchiyama","Chiba Ken","04","Sosa Shi","7465522","","","35.5168","140.1954","1"],"289-2172":["JP","289-2172","Negoya","Chiba Ken","04","Sosa Shi","7465522","","","35.5168","140.1954","1"],"289-2173":["JP","289-2173","Iidaka","Chiba Ken","04","Sosa Shi","7465522","","","35.5168","140.1954","1"],"289-2174":["JP","289-2174","Kozaki","Chiba Ken","04","Sosa Shi","7465522","","","35.6998","140.5538","4"],"289-2175":["JP","289-2175","Katako","Chiba Ken","04","Sosa Shi","7465522","","","35.5168","140.1954","1"],"289-2176":["JP","289-2176","Ohori","Chiba Ken","04","Sosa Shi","7465522","","","35.6998","140.5538","4"],"289-2177":["JP","289-2177","Kanabara","Chiba Ken","04","Sosa Shi","7465522","","","35.5168","140.1954","1"],"289-2178":["JP","289-2178","Aguyama","Chiba Ken","04","Sosa Shi","7465522","","","35.5168","140.1954","1"],"289-2179":["JP","289-2179","Odaka","Chiba Ken","04","Sosa Shi","7465522","","","35.6998","140.5538","4"],"289-3181":["JP","289-3181","Node","Chiba Ken","04","Sosa Shi","7465522","","","35.6667","140.5833","4"],"289-3182":["JP","289-3182","Imaizumi","Chiba Ken","04","Sosa Shi","7465522","","","35.6998","140.5538","4"],"289-3183":["JP","289-3183","Niibori","Chiba Ken","04","Sosa Shi","7465522","","","35.4157","140.2959","1"],"289-3184":["JP","289-3184","Kayada","Chiba Ken","04","Sosa Shi","7465522","","","35.4157","140.2959","1"],"289-3185":["JP","289-3185","Horikawa","Chiba Ken","04","Sosa Shi","7465522","","","35.6998","140.5538","4"],"289-3186":["JP","289-3186","Kawabe","Chiba Ken","04","Sosa Shi","7465522","","","35.6998","140.5538","4"],"289-1201":["JP","289-1201","Itagawa","Chiba Ken","04","Sammu Shi","7465523","","","35.3742","140.1657","1"],"289-1202":["JP","289-1202","Nakatsuta","Chiba Ken","04","Sammu Shi","7465523","","","35.3742","140.1657","1"],"289-1203":["JP","289-1203","Asoshinden","Chiba Ken","04","Sammu Shi","7465523","","","35.3742","140.1657","1"],"289-1204":["JP","289-1204","Toda","Chiba Ken","04","Sammu Shi","7465523","","","35.3742","140.1657","1"],"289-1205":["JP","289-1205","Shiizaki","Chiba Ken","04","Sammu Shi","7465523","","","35.3742","140.1657","1"],"289-1206":["JP","289-1206","Hyugadai","Chiba Ken","04","Sammu Shi","7465523","","","35.3742","140.1657","1"],"289-1211":["JP","289-1211","Ogi","Chiba Ken","04","Sammu Shi","7465523","","","35.3605","140.3094","1"],"289-1212":["JP","289-1212","Kibara","Chiba Ken","04","Sammu Shi","7465523","","","35.3605","140.3094","1"],"289-1213":["JP","289-1213","Ametsubo","Chiba Ken","04","Sammu Shi","7465523","","","35.3605","140.3094","1"],"289-1214":["JP","289-1214","Mori","Chiba Ken","04","Sammu Shi","7465523","","","35.624","140.4209","4"],"289-1215":["JP","289-1215","Yabe","Chiba Ken","04","Sammu Shi","7465523","","","35.3605","140.3094","1"],"289-1216":["JP","289-1216","Uekusa","Chiba Ken","04","Sammu Shi","7465523","","","35.3605","140.3094","1"],"289-1217":["JP","289-1217","Shimofuda","Chiba Ken","04","Sammu Shi","7465523","","","35.3605","140.3094","1"],"289-1218":["JP","289-1218","Musho","Chiba Ken","04","Sammu Shi","7465523","","","35.3605","140.3094","1"],"289-1221":["JP","289-1221","Sanekado","Chiba Ken","04","Sammu Shi","7465523","","","35.388","140.022","1"],"289-1222":["JP","289-1222","Itanakashinden","Chiba Ken","04","Sammu Shi","7465523","","","35.388","140.022","1"],"289-1223":["JP","289-1223","Haniya","Chiba Ken","04","Sammu Shi","7465523","","","35.388","140.022","1"],"289-1224":["JP","289-1224","Misugino","Chiba Ken","04","Sammu Shi","7465523","","","35.388","140.022","1"],"289-1225":["JP","289-1225","Okiwatashi","Chiba Ken","04","Sammu Shi","7465523","","","35.388","140.022","1"],"289-1226":["JP","289-1226","Yokota","Chiba Ken","04","Sammu Shi","7465523","","","35.624","140.4209","4"],"289-1300":["JP","289-1300","Ikanikeisaiganaibaai","Chiba Ken","04","Sammu Shi","7465523","","","35.1521","140.2373","1"],"289-1301":["JP","289-1301","Kido","Chiba Ken","04","Sammu Shi","7465523","","","35.624","140.4209","4"],"289-1302":["JP","289-1302","Komatsu","Chiba Ken","04","Sammu Shi","7465523","","","35.1521","140.2373","1"],"289-1303":["JP","289-1303","Matsugaya","Chiba Ken","04","Sammu Shi","7465523","","","35.1521","140.2373","1"],"289-1304":["JP","289-1304","Inochi","Chiba Ken","04","Sammu Shi","7465523","","","35.1521","140.2373","1"],"289-1305":["JP","289-1305","Motosuka","Chiba Ken","04","Sammu Shi","7465523","","","35.1521","140.2373","1"],"289-1306":["JP","289-1306","Shirahata","Chiba Ken","04","Sammu Shi","7465523","","","35.1521","140.2373","1"],"289-1311":["JP","289-1311","Hayafune","Chiba Ken","04","Sammu Shi","7465523","","","35.3946","140.3309","1"],"289-1312":["JP","289-1312","Shibahara","Chiba Ken","04","Sammu Shi","7465523","","","35.624","140.4209","4"],"289-1313":["JP","289-1313","Kamiyokoji","Chiba Ken","04","Sammu Shi","7465523","","","35.3946","140.3309","1"],"289-1314":["JP","289-1314","Shimoyokoji","Chiba Ken","04","Sammu Shi","7465523","","","35.3946","140.3309","1"],"289-1315":["JP","289-1315","Kusabuka","Chiba Ken","04","Sammu Shi","7465523","","","35.3946","140.3309","1"],"289-1316":["JP","289-1316","Gokita","Chiba Ken","04","Sammu Shi","7465523","","","35.3946","140.3309","1"],"289-1317":["JP","289-1317","Koizumi","Chiba Ken","04","Sammu Shi","7465523","","","35.624","140.4209","4"],"289-1318":["JP","289-1318","Terazaki","Chiba Ken","04","Sammu Shi","7465523","","","35.3946","140.3309","1"],"289-1321":["JP","289-1321","Tomida","Chiba Ken","04","Sammu Shi","7465523","","","35.624","140.4209","4"],"289-1322":["JP","289-1322","Tomidagoya","Chiba Ken","04","Sammu Shi","7465523","","","35.4009","140.2634","1"],"289-1323":["JP","289-1323","Tomiguchi","Chiba Ken","04","Sammu Shi","7465523","","","35.4009","140.2634","1"],"289-1324":["JP","289-1324","Tonodai","Chiba Ken","04","Sammu Shi","7465523","","","35.4009","140.2634","1"],"289-1325":["JP","289-1325","Shima","Chiba Ken","04","Sammu Shi","7465523","","","35.624","140.4209","4"],"289-1326":["JP","289-1326","Naruto","Chiba Ken","04","Sammu Shi","7465523","","","35.6","140.4167","4"],"289-1327":["JP","289-1327","Himeshima","Chiba Ken","04","Sammu Shi","7465523","","","35.4009","140.2634","1"],"289-1328":["JP","289-1328","Yusaka","Chiba Ken","04","Sammu Shi","7465523","","","35.4009","140.2634","1"],"289-1331":["JP","289-1331","Kawasaki","Chiba Ken","04","Sammu Shi","7465523","","","35.624","140.4209","4"],"289-1332":["JP","289-1332","Oyada","Chiba Ken","04","Sammu Shi","7465523","","","35.2347","140.1595","1"],"289-1333":["JP","289-1333","Ichiba","Chiba Ken","04","Sammu Shi","7465523","","","35.624","140.4209","4"],"289-1334":["JP","289-1334","Wada","Chiba Ken","04","Sammu Shi","7465523","","","35.624","140.4209","4"],"289-1335":["JP","289-1335","Itatsuki","Chiba Ken","04","Sammu Shi","7465523","","","35.2347","140.1595","1"],"289-1341":["JP","289-1341","Nobori","Chiba Ken","04","Sammu Shi","7465523","","","35.1295","140.08","1"],"289-1342":["JP","289-1342","Shimado","Chiba Ken","04","Sammu Shi","7465523","","","35.1295","140.08","1"],"289-1343":["JP","289-1343","Shingyoji","Chiba Ken","04","Sammu Shi","7465523","","","35.1295","140.08","1"],"289-1344":["JP","289-1344","Niinomi","Chiba Ken","04","Sammu Shi","7465523","","","35.1295","140.08","1"],"289-1345":["JP","289-1345","Tsube","Chiba Ken","04","Sammu Shi","7465523","","","35.624","140.4209","4"],"289-1501":["JP","289-1501","Matsuomachi Yamamuro","Chiba Ken","04","Sammu Shi","7465523","","","35.4161","140.1567","1"],"289-1502":["JP","289-1502","Matsuomachi Hikkoshi","Chiba Ken","04","Sammu Shi","7465523","","","35.4161","140.1567","1"],"289-1503":["JP","289-1503","Matsuomachi Yatsu","Chiba Ken","04","Sammu Shi","7465523","","","35.4161","140.1567","1"],"289-1504":["JP","289-1504","Matsuomachi Kowa","Chiba Ken","04","Sammu Shi","7465523","","","35.4161","140.1567","1"],"289-1505":["JP","289-1505","Matsuomachi Kanno","Chiba Ken","04","Sammu Shi","7465523","","","35.4161","140.1567","1"],"289-1506":["JP","289-1506","Matsuomachi Kamiokura","Chiba Ken","04","Sammu Shi","7465523","","","35.4161","140.1567","1"],"289-1507":["JP","289-1507","Matsuomachi Ogawa","Chiba Ken","04","Sammu Shi","7465523","","","35.4161","140.1567","1"],"289-1511":["JP","289-1511","Matsuomachi Kaburaki","Chiba Ken","04","Sammu Shi","7465523","","","35.4161","140.1567","1"],"289-1512":["JP","289-1512","Matsuomachi Hatta","Chiba Ken","04","Sammu Shi","7465523","","","35.4161","140.1567","1"],"289-1513":["JP","289-1513","Matsuomachi Saruo","Chiba Ken","04","Sammu Shi","7465523","","","35.4161","140.1567","1"],"289-1514":["JP","289-1514","Matsuomachi Matsuo","Chiba Ken","04","Sammu Shi","7465523","","","35.4161","140.1567","1"],"289-1515":["JP","289-1515","Matsuomachi Fujimidai","Chiba Ken","04","Sammu Shi","7465523","","","35.4161","140.1567","1"],"289-1516":["JP","289-1516","Matsuomachi Takoe","Chiba Ken","04","Sammu Shi","7465523","","","35.4161","140.1567","1"],"289-1517":["JP","289-1517","Matsuomachi Shimookura","Chiba Ken","04","Sammu Shi","7465523","","","35.4161","140.1567","1"],"289-1521":["JP","289-1521","Matsuomachi Motogashiwa","Chiba Ken","04","Sammu Shi","7465523","","","35.4161","140.1567","1"],"289-1522":["JP","289-1522","Matsuomachi Takatomi","Chiba Ken","04","Sammu Shi","7465523","","","35.4161","140.1567","1"],"289-1523":["JP","289-1523","Matsuomachi Gotanda","Chiba Ken","04","Sammu Shi","7465523","","","35.4161","140.1567","1"],"289-1524":["JP","289-1524","Matsuomachi Iwaita","Chiba Ken","04","Sammu Shi","7465523","","","35.4161","140.1567","1"],"289-1525":["JP","289-1525","Matsuomachi Motomizufuka","Chiba Ken","04","Sammu Shi","7465523","","","35.4161","140.1567","1"],"289-1526":["JP","289-1526","Matsuomachi Mizufuka","Chiba Ken","04","Sammu Shi","7465523","","","35.4161","140.1567","1"],"289-1527":["JP","289-1527","Matsuomachi Otsutsumi","Chiba Ken","04","Sammu Shi","7465523","","","35.4161","140.1567","1"],"289-1531":["JP","289-1531","Matsuomachi Kigatana","Chiba Ken","04","Sammu Shi","7465523","","","35.4161","140.1567","1"],"289-1532":["JP","289-1532","Matsuomachi Takenosato","Chiba Ken","04","Sammu Shi","7465523","","","35.4161","140.1567","1"],"289-1533":["JP","289-1533","Matsuomachi Hirone","Chiba Ken","04","Sammu Shi","7465523","","","35.4161","140.1567","1"],"289-1534":["JP","289-1534","Matsuomachi Shimono","Chiba Ken","04","Sammu Shi","7465523","","","35.4161","140.1567","1"],"289-1535":["JP","289-1535","Matsuomachi Orito","Chiba Ken","04","Sammu Shi","7465523","","","35.4161","140.1567","1"],"289-1536":["JP","289-1536","Matsuomachi Shimonogo","Chiba Ken","04","Sammu Shi","7465523","","","35.4161","140.1567","1"],"289-1537":["JP","289-1537","Matsuomachi Kashikehongo","Chiba Ken","04","Sammu Shi","7465523","","","35.4161","140.1567","1"],"289-1801":["JP","289-1801","Hasunuma I","Chiba Ken","04","Sammu Shi","7465523","","","35.4161","140.1567","1"],"289-1802":["JP","289-1802","Hasunuma Ro","Chiba Ken","04","Sammu Shi","7465523","","","35.4161","140.1567","1"],"289-1803":["JP","289-1803","Hasunuma Ho","Chiba Ken","04","Sammu Shi","7465523","","","35.4161","140.1567","1"],"289-1804":["JP","289-1804","Hasunuma Hira","Chiba Ken","04","Sammu Shi","7465523","","","35.4161","140.1567","1"],"289-1805":["JP","289-1805","Hasunuma Ni","Chiba Ken","04","Sammu Shi","7465523","","","35.4161","140.1567","1"],"289-1806":["JP","289-1806","Hasunuma Ha","Chiba Ken","04","Sammu Shi","7465523","","","35.4161","140.1567","1"],"289-1100":["JP","289-1100","Ikanikeisaiganaibaai","Chiba Ken","04","Yachimata Shi","8304238","","","35.3534","139.9759","1"],"289-1101":["JP","289-1101","Asahi","Chiba Ken","04","Yachimata Shi","8304238","","","35.6423","140.2968","4"],"289-1102":["JP","289-1102","Okiwatashi","Chiba Ken","04","Yachimata Shi","8304238","","","35.3534","139.9759","1"],"289-1103":["JP","289-1103","Yachimatani","Chiba Ken","04","Yachimata Shi","8304238","","","35.3534","139.9759","1"],"289-1104":["JP","289-1104","Hijikai","Chiba Ken","04","Yachimata Shi","8304238","","","35.3534","139.9759","1"],"289-1105":["JP","289-1105","Izumidai","Chiba Ken","04","Yachimata Shi","8304238","","","35.6423","140.2968","4"],"289-1106":["JP","289-1106","Enokido","Chiba Ken","04","Yachimata Shi","8304238","","","35.6423","140.2968","4"],"289-1107":["JP","289-1107","Yachimataha","Chiba Ken","04","Yachimata Shi","8304238","","","35.3534","139.9759","1"],"289-1108":["JP","289-1108","Gammaru","Chiba Ken","04","Yachimata Shi","8304238","","","35.3534","139.9759","1"],"289-1111":["JP","289-1111","Ogi","Chiba Ken","04","Yachimata Shi","8304238","","","35.6092","140.123","1"],"289-1112":["JP","289-1112","Kibara","Chiba Ken","04","Yachimata Shi","8304238","","","35.6092","140.123","1"],"289-1113":["JP","289-1113","Yachimatahe","Chiba Ken","04","Yachimata Shi","8304238","","","35.6092","140.123","1"],"289-1114":["JP","289-1114","Higashiyoshida","Chiba Ken","04","Yachimata Shi","8304238","","","35.6092","140.123","1"],"289-1115":["JP","289-1115","Yachimataho","Chiba Ken","04","Yachimata Shi","8304238","","","35.6092","140.123","1"],"289-1116":["JP","289-1116","Chuo","Chiba Ken","04","Yachimata Shi","8304238","","","35.6423","140.2968","4"],"289-1121":["JP","289-1121","Isago","Chiba Ken","04","Yachimata Shi","8304238","","","35.5144","139.9948","1"],"289-1122":["JP","289-1122","Shimoku","Chiba Ken","04","Yachimata Shi","8304238","","","35.5144","139.9948","1"],"289-1123":["JP","289-1123","Takidai","Chiba Ken","04","Yachimata Shi","8304238","","","35.5144","139.9948","1"],"289-1124":["JP","289-1124","Yamadadai","Chiba Ken","04","Yachimata Shi","8304238","","","35.5144","139.9948","1"],"289-1125":["JP","289-1125","Kamiisago","Chiba Ken","04","Yachimata Shi","8304238","","","35.5144","139.9948","1"],"289-1126":["JP","289-1126","Oki","Chiba Ken","04","Yachimata Shi","8304238","","","35.5144","139.9948","1"],"289-1131":["JP","289-1131","Kibogaoka","Chiba Ken","04","Yachimata Shi","8304238","","","35.5144","139.9948","1"],"289-1132":["JP","289-1132","Seta","Chiba Ken","04","Yachimata Shi","8304238","","","35.5144","139.9948","1"],"289-1133":["JP","289-1133","Yoshikura","Chiba Ken","04","Yachimata Shi","8304238","","","35.5144","139.9948","1"],"289-1134":["JP","289-1134","Oyaru","Chiba Ken","04","Yachimata Shi","8304238","","","35.5144","139.9948","1"],"289-1135":["JP","289-1135","Koyaru","Chiba Ken","04","Yachimata Shi","8304238","","","35.5144","139.9948","1"],"289-1136":["JP","289-1136","Negoya","Chiba Ken","04","Yachimata Shi","8304238","","","35.5144","139.9948","1"],"289-1137":["JP","289-1137","Okada","Chiba Ken","04","Yachimata Shi","8304238","","","35.5144","139.9948","1"],"289-1138":["JP","289-1138","Mochikusa","Chiba Ken","04","Yachimata Shi","8304238","","","35.5144","139.9948","1"],"289-1141":["JP","289-1141","Toyama","Chiba Ken","04","Yachimata Shi","8304238","","","35.9029","139.9231","1"],"289-1142":["JP","289-1142","Oseki","Chiba Ken","04","Yachimata Shi","8304238","","","35.9029","139.9231","1"],"289-1143":["JP","289-1143","Yachimatai","Chiba Ken","04","Yachimata Shi","8304238","","","35.9029","139.9231","1"],"289-1144":["JP","289-1144","Yachimataro","Chiba Ken","04","Yachimata Shi","8304238","","","35.9029","139.9231","1"],"289-1145":["JP","289-1145","Midoridai","Chiba Ken","04","Yachimata Shi","8304238","","","35.6423","140.2968","4"]}