{"555-0000":["JP","555-0000","Ikanikeisaiganaibaai","Osaka Fu","32","Osaka Shi","1853897","Nishiyodogawa Ku","27113","34.6883","135.4582","1"],"555-0001":["JP","555-0001","Tsukuda","Osaka Fu","32","Osaka Shi","1853897","Nishiyodogawa Ku","27113","34.7132","135.4411","1"],"555-0011":["JP","555-0011","Takeshima","Osaka Fu","32","Osaka Shi","1853897","Nishiyodogawa Ku","27113","34.7255","135.4521","1"],"555-0012":["JP","555-0012","Mitejima","Osaka Fu","32","Osaka Shi","1853897","Nishiyodogawa Ku","27113","34.7162","135.4543","4"],"555-0013":["JP","555-0013","Chibune","Osaka Fu","32","Osaka Shi","1853897","Nishiyodogawa Ku","27113","34.7101","135.4519","1"],"555-0021":["JP","555-0021","Utajima","Osaka Fu","32","Osaka Shi","1853897","Nishiyodogawa Ku","27113","34.7154","135.4628","1"],"555-0022":["JP","555-0022","Kashiwazato","Osaka Fu","32","Osaka Shi","1853897","Nishiyodogawa Ku","27113","34.711","135.4676","1"],"555-0023":["JP","555-0023","Hanakawa","Osaka Fu","32","Osaka Shi","1853897","Nishiyodogawa Ku","27113","34.7077","135.4661","1"],"555-0024":["JP","555-0024","Nozato","Osaka Fu","32","Osaka Shi","1853897","Nishiyodogawa Ku","27113","34.7094","135.4644","4"],"555-0025":["JP","555-0025","Himesato","Osaka Fu","32","Osaka Shi","1853897","Nishiyodogawa Ku","27113","34.7061","135.4593","1"],"555-0031":["JP","555-0031","Dekijima","Osaka Fu","32","Osaka Shi","1853897","Nishiyodogawa Ku","27113","34.7058","135.4372","1"],"555-0032":["JP","555-0032","Owada","Osaka Fu","32","Osaka Shi","1853897","Nishiyodogawa Ku","27113","34.7065","135.4443","1"],"555-0033":["JP","555-0033","Himeshima","Osaka Fu","32","Osaka Shi","1853897","Nishiyodogawa Ku","27113","34.7024","135.4524","1"],"555-0034":["JP","555-0034","Fukumachi","Osaka Fu","32","Osaka Shi","1853897","Nishiyodogawa Ku","27113","34.6976","135.4433","4"],"555-0041":["JP","555-0041","Nakashima","Osaka Fu","32","Osaka Shi","1853897","Nishiyodogawa Ku","27113","34.7","135.4221","1"],"555-0042":["JP","555-0042","Nishishima","Osaka Fu","32","Osaka Shi","1853897","Nishiyodogawa Ku","27113","34.6966","135.4304","1"],"555-0043":["JP","555-0043","Ono","Osaka Fu","32","Osaka Shi","1853897","Nishiyodogawa Ku","27113","34.7005","135.4382","1"],"555-0044":["JP","555-0044","Hyakushima","Osaka Fu","32","Osaka Shi","1853897","Nishiyodogawa Ku","27113","34.6955","135.4365","1"]}