{"600-0000":["JP","600-0000","Ikanikeisaiganaibaai","Kyoto Fu","22","Kyoto Shi","1857906","Shimogyo Ku","26106","34.95","135.8167","1"],"600-8001":["JP","600-8001","Shincho","Kyoto Fu","22","Kyoto Shi","1857906","Shimogyo Ku","26106","34.95","135.8167","1"],"600-8002":["JP","600-8002","Otabicho","Kyoto Fu","22","Kyoto Shi","1857906","Shimogyo Ku","26106","34.95","135.8167","1"],"600-8003":["JP","600-8003","Otabimiyamotocho","Kyoto Fu","22","Kyoto Shi","1857906","Shimogyo Ku","26106","34.95","135.8167","1"],"600-8004":["JP","600-8004","Naramonocho","Kyoto Fu","22","Kyoto Shi","1857906","Shimogyo Ku","26106","34.95","135.8167","1"],"600-8005":["JP","600-8005","Tachiuri Higashicho","Kyoto Fu","22","Kyoto Shi","1857906","Shimogyo Ku","26106","34.95","135.8167","1"],"600-8006":["JP","600-8006","Tachiuri Nakanocho","Kyoto Fu","22","Kyoto Shi","1857906","Shimogyo Ku","26106","34.95","135.8167","1"],"600-8007":["JP","600-8007","Tachiuri Nishimachi","Kyoto Fu","22","Kyoto Shi","1857906","Shimogyo Ku","26106","34.95","135.8167","1"],"600-8008":["JP","600-8008","Naginatabokocho","Kyoto Fu","22","Kyoto Shi","1857906","Shimogyo Ku","26106","34.95","135.8167","1"],"600-8009":["JP","600-8009","Kankobokocho","Kyoto Fu","22","Kyoto Shi","1857906","Shimogyo Ku","26106","34.95","135.8167","1"],"600-8011":["JP","600-8011","Hashimotocho","Kyoto Fu","22","Kyoto Shi","1857906","Shimogyo Ku","26106","34.95","135.8167","1"],"600-8012":["JP","600-8012","Saitocho","Kyoto Fu","22","Kyoto Shi","1857906","Shimogyo Ku","26106","34.95","135.8167","1"],"600-8013":["JP","600-8013","Tennocho","Kyoto Fu","22","Kyoto Shi","1857906","Shimogyo Ku","26106","34.95","135.8167","1"],"600-8014":["JP","600-8014","Izumiyacho","Kyoto Fu","22","Kyoto Shi","1857906","Shimogyo Ku","26106","34.95","135.8167","1"],"600-8015":["JP","600-8015","Minoyacho","Kyoto Fu","22","Kyoto Shi","1857906","Shimogyo Ku","26106","34.95","135.8167","1"],"600-8016":["JP","600-8016","Zaimokucho","Kyoto Fu","22","Kyoto Shi","1857906","Shimogyo Ku","26106","34.95","135.8167","1"],"600-8017":["JP","600-8017","Shimozaimokucho","Kyoto Fu","22","Kyoto Shi","1857906","Shimogyo Ku","26106","34.95","135.8167","1"],"600-8018":["JP","600-8018","Ichinocho","Kyoto Fu","22","Kyoto Shi","1857906","Shimogyo Ku","26106","34.95","135.8167","1"],"600-8019":["JP","600-8019","Sendocho","Kyoto Fu","22","Kyoto Shi","1857906","Shimogyo Ku","26106","34.95","135.8167","1"],"600-8020":["JP","600-8020","Mikagedomaecho","Kyoto Fu","22","Kyoto Shi","1857906","Shimogyo Ku","26106","34.95","135.8167","1"],"600-8021":["JP","600-8021","Jumpucho","Kyoto Fu","22","Kyoto Shi","1857906","Shimogyo Ku","26106","34.95","135.8167","1"],"600-8022":["JP","600-8022","Inaricho(Kawaramachidorishijosagaru","Kyoto Fu","22","Kyoto Shi","1857906","Shimogyo Ku","26106","34.95","135.8167","1"],"600-8023":["JP","600-8023","Tominagacho","Kyoto Fu","22","Kyoto Shi","1857906","Shimogyo Ku","26106","34.95","135.8167","1"],"600-8024":["JP","600-8024","Temmacho","Kyoto Fu","22","Kyoto Shi","1857906","Shimogyo Ku","26106","34.95","135.8167","1"],"600-8025":["JP","600-8025","Shimizucho","Kyoto Fu","22","Kyoto Shi","1857906","Shimogyo Ku","26106","34.95","135.8167","1"],"600-8026":["JP","600-8026","Matsukawacho","Kyoto Fu","22","Kyoto Shi","1857906","Shimogyo Ku","26106","34.95","135.8167","1"],"600-8027":["JP","600-8027","Nambacho","Kyoto Fu","22","Kyoto Shi","1857906","Shimogyo Ku","26106","34.95","135.8167","1"],"600-8028":["JP","600-8028","Uematsucho","Kyoto Fu","22","Kyoto Shi","1857906","Shimogyo Ku","26106","34.95","135.8167","1"],"600-8029":["JP","600-8029","Nishihashizumecho","Kyoto Fu","22","Kyoto Shi","1857906","Shimogyo Ku","26106","34.95","135.8167","1"],"600-8031":["JP","600-8031","Teiammaenocho","Kyoto Fu","22","Kyoto Shi","1857906","Shimogyo Ku","26106","34.95","135.8167","1"],"600-8032":["JP","600-8032","Nakanocho","Kyoto Fu","22","Kyoto Shi","1857906","Shimogyo Ku","26106","34.95","135.8167","1"],"600-8033":["JP","600-8033","Ebisunocho","Kyoto Fu","22","Kyoto Shi","1857906","Shimogyo Ku","26106","34.95","135.8167","1"],"600-8034":["JP","600-8034","Kotakecho","Kyoto Fu","22","Kyoto Shi","1857906","Shimogyo Ku","26106","34.95","135.8167","1"],"600-8035":["JP","600-8035","Kyogokucho","Kyoto Fu","22","Kyoto Shi","1857906","Shimogyo Ku","26106","34.95","135.8167","1"],"600-8036":["JP","600-8036","Chamayacho(Takatsujidorigokomachihi","Kyoto Fu","22","Kyoto Shi","1857906","Shimogyo Ku","26106","34.95","135.8167","1"],"600-8037":["JP","600-8037","Maruyacho(Gokomachidoriayanokojisag","Kyoto Fu","22","Kyoto Shi","1857906","Shimogyo Ku","26106","34.95","135.8167","1"],"600-8038":["JP","600-8038","Tabiyacho","Kyoto Fu","22","Kyoto Shi","1857906","Shimogyo Ku","26106","34.95","135.8167","1"],"600-8039":["JP","600-8039","Daizucho","Kyoto Fu","22","Kyoto Shi","1857906","Shimogyo Ku","26106","34.95","135.8167","1"],"600-8040":["JP","600-8040","Azuchicho","Kyoto Fu","22","Kyoto Shi","1857906","Shimogyo Ku","26106","34.95","135.8167","1"],"600-8041":["JP","600-8041","Hachimonjicho","Kyoto Fu","22","Kyoto Shi","1857906","Shimogyo Ku","26106","34.95","135.8167","1"],"600-8042":["JP","600-8042","Tawarayacho(Fuyachodoriayanokojisag","Kyoto Fu","22","Kyoto Shi","1857906","Shimogyo Ku","26106","34.95","135.8167","1"],"600-8043":["JP","600-8043","Daikokucho","Kyoto Fu","22","Kyoto Shi","1857906","Shimogyo Ku","26106","34.95","135.8167","1"],"600-8044":["JP","600-8044","Tachibanacho","Kyoto Fu","22","Kyoto Shi","1857906","Shimogyo Ku","26106","34.95","135.8167","1"],"600-8045":["JP","600-8045","Chamayacho(Takatsujidorigokomachini","Kyoto Fu","22","Kyoto Shi","1857906","Shimogyo Ku","26106","34.95","135.8167","1"],"600-8046":["JP","600-8046","Masuyacho","Kyoto Fu","22","Kyoto Shi","1857906","Shimogyo Ku","26106","34.95","135.8167","1"],"600-8047":["JP","600-8047","Ishifudonocho","Kyoto Fu","22","Kyoto Shi","1857906","Shimogyo Ku","26106","34.95","135.8167","1"],"600-8048":["JP","600-8048","Subamacho","Kyoto Fu","22","Kyoto Shi","1857906","Shimogyo Ku","26106","34.95","135.8167","1"],"600-8049":["JP","600-8049","Katadacho(Manjujidorigokomachinishi","Kyoto Fu","22","Kyoto Shi","1857906","Shimogyo Ku","26106","34.95","135.8167","1"],"600-8050":["JP","600-8050","Katadacho(Manshujidoritominokojihig","Kyoto Fu","22","Kyoto Shi","1857906","Shimogyo Ku","26106","34.95","135.8167","1"],"600-8051":["JP","600-8051","Tokushojicho","Kyoto Fu","22","Kyoto Shi","1857906","Shimogyo Ku","26106","34.95","135.8167","1"],"600-8052":["JP","600-8052","Shioyacho","Kyoto Fu","22","Kyoto Shi","1857906","Shimogyo Ku","26106","34.95","135.8167","1"],"600-8053":["JP","600-8053","Nushiyacho(Tominokojidoriayanokojis","Kyoto Fu","22","Kyoto Shi","1857906","Shimogyo Ku","26106","34.95","135.8167","1"],"600-8054":["JP","600-8054","Bukkoji Higashimachi","Kyoto Fu","22","Kyoto Shi","1857906","Shimogyo Ku","26106","34.95","135.8167","1"],"600-8055":["JP","600-8055","Nabeyacho","Kyoto Fu","22","Kyoto Shi","1857906","Shimogyo Ku","26106","34.95","135.8167","1"],"600-8056":["JP","600-8056","Kariganecho(Takatsujidoritominokoji","Kyoto Fu","22","Kyoto Shi","1857906","Shimogyo Ku","26106","34.95","135.8167","1"],"600-8057":["JP","600-8057","Kagiyacho","Kyoto Fu","22","Kyoto Shi","1857906","Shimogyo Ku","26106","34.95","135.8167","1"],"600-8058":["JP","600-8058","Kamiurokogatacho","Kyoto Fu","22","Kyoto Shi","1857906","Shimogyo Ku","26106","34.95","135.8167","1"],"600-8059":["JP","600-8059","Shimorokogatacho","Kyoto Fu","22","Kyoto Shi","1857906","Shimogyo Ku","26106","34.95","135.8167","1"],"600-8060":["JP","600-8060","Kariganecho(Takatsujidoritominokoji","Kyoto Fu","22","Kyoto Shi","1857906","Shimogyo Ku","26106","34.95","135.8167","1"],"600-8061":["JP","600-8061","Sujiyacho","Kyoto Fu","22","Kyoto Shi","1857906","Shimogyo Ku","26106","34.95","135.8167","1"],"600-8062":["JP","600-8062","Ebisuyacho","Kyoto Fu","22","Kyoto Shi","1857906","Shimogyo Ku","26106","34.95","135.8167","1"],"600-8063":["JP","600-8063","Matsubaranakanocho","Kyoto Fu","22","Kyoto Shi","1857906","Shimogyo Ku","26106","34.95","135.8167","1"],"600-8064":["JP","600-8064","Motokamishimmeicho","Kyoto Fu","22","Kyoto Shi","1857906","Shimogyo Ku","26106","34.95","135.8167","1"],"600-8065":["JP","600-8065","Motoshimmeicho","Kyoto Fu","22","Kyoto Shi","1857906","Shimogyo Ku","26106","34.95","135.8167","1"],"600-8066":["JP","600-8066","Kashiwayacho","Kyoto Fu","22","Kyoto Shi","1857906","Shimogyo Ku","26106","34.95","135.8167","1"],"600-8067":["JP","600-8067","Katadacho","Kyoto Fu","22","Kyoto Shi","1857906","Shimogyo Ku","26106","34.95","135.8167","1"],"600-8068":["JP","600-8068","Chuancho","Kyoto Fu","22","Kyoto Shi","1857906","Shimogyo Ku","26106","34.95","135.8167","1"],"600-8069":["JP","600-8069","Kichimonjicho","Kyoto Fu","22","Kyoto Shi","1857906","Shimogyo Ku","26106","34.95","135.8167","1"],"600-8070":["JP","600-8070","Tawarayacho","Kyoto Fu","22","Kyoto Shi","1857906","Shimogyo Ku","26106","34.95","135.8167","1"],"600-8071":["JP","600-8071","Ainocho","Kyoto Fu","22","Kyoto Shi","1857906","Shimogyo Ku","26106","34.95","135.8167","1"],"600-8072":["JP","600-8072","Ayazaimokucho","Kyoto Fu","22","Kyoto Shi","1857906","Shimogyo Ku","26106","34.95","135.8167","1"],"600-8073":["JP","600-8073","Nagaharacho","Kyoto Fu","22","Kyoto Shi","1857906","Shimogyo Ku","26106","34.95","135.8167","1"],"600-8074":["JP","600-8074","Higashimaecho","Kyoto Fu","22","Kyoto Shi","1857906","Shimogyo Ku","26106","34.95","135.8167","1"],"600-8075":["JP","600-8075","Marikojicho","Kyoto Fu","22","Kyoto Shi","1857906","Shimogyo Ku","26106","34.95","135.8167","1"],"600-8076":["JP","600-8076","Senshojicho","Kyoto Fu","22","Kyoto Shi","1857906","Shimogyo Ku","26106","34.95","135.8167","1"],"600-8077":["JP","600-8077","Yugaocho","Kyoto Fu","22","Kyoto Shi","1857906","Shimogyo Ku","26106","34.95","135.8167","1"],"600-8078":["JP","600-8078","Sugiyacho","Kyoto Fu","22","Kyoto Shi","1857906","Shimogyo Ku","26106","34.95","135.8167","1"],"600-8079":["JP","600-8079","Kajiyacho(Sakaimachidorimatsubarasa","Kyoto Fu","22","Kyoto Shi","1857906","Shimogyo Ku","26106","34.95","135.8167","1"],"600-8081":["JP","600-8081","Koishicho","Kyoto Fu","22","Kyoto Shi","1857906","Shimogyo Ku","26106","34.95","135.8167","1"],"600-8082":["JP","600-8082","Takazaimokucho","Kyoto Fu","22","Kyoto Shi","1857906","Shimogyo Ku","26106","34.95","135.8167","1"],"600-8083":["JP","600-8083","Nishimaecho","Kyoto Fu","22","Kyoto Shi","1857906","Shimogyo Ku","26106","34.95","135.8167","1"],"600-8084":["JP","600-8084","Shinkaicho","Kyoto Fu","22","Kyoto Shi","1857906","Shimogyo Ku","26106","34.95","135.8167","1"],"600-8085":["JP","600-8085","Tsuzurayacho","Kyoto Fu","22","Kyoto Shi","1857906","Shimogyo Ku","26106","34.95","135.8167","1"],"600-8086":["JP","600-8086","Hontorocho","Kyoto Fu","22","Kyoto Shi","1857906","Shimogyo Ku","26106","34.95","135.8167","1"],"600-8087":["JP","600-8087","Hinoshitacho","Kyoto Fu","22","Kyoto Shi","1857906","Shimogyo Ku","26106","34.95","135.8167","1"],"600-8088":["JP","600-8088","Kanshadencho","Kyoto Fu","22","Kyoto Shi","1857906","Shimogyo Ku","26106","34.95","135.8167","1"],"600-8089":["JP","600-8089","Katadacho(Manshujidorisakaimachinis","Kyoto Fu","22","Kyoto Shi","1857906","Shimogyo Ku","26106","34.95","135.8167","1"],"600-8090":["JP","600-8090","Takeyanocho","Kyoto Fu","22","Kyoto Shi","1857906","Shimogyo Ku","26106","34.95","135.8167","1"],"600-8091":["JP","600-8091","Motoakuojicho","Kyoto Fu","22","Kyoto Shi","1857906","Shimogyo Ku","26106","34.95","135.8167","1"],"600-8092":["JP","600-8092","Shimmeicho","Kyoto Fu","22","Kyoto Shi","1857906","Shimogyo Ku","26106","34.95","135.8167","1"],"600-8093":["JP","600-8093","Takeyacho","Kyoto Fu","22","Kyoto Shi","1857906","Shimogyo Ku","26106","34.95","135.8167","1"],"600-8094":["JP","600-8094","Bukkoji Nishimachi","Kyoto Fu","22","Kyoto Shi","1857906","Shimogyo Ku","26106","34.95","135.8167","1"],"600-8095":["JP","600-8095","Ogisakayacho","Kyoto Fu","22","Kyoto Shi","1857906","Shimogyo Ku","26106","34.95","135.8167","1"],"600-8096":["JP","600-8096","Takahashicho","Kyoto Fu","22","Kyoto Shi","1857906","Shimogyo Ku","26106","34.95","135.8167","1"],"600-8097":["JP","600-8097","Sangencho","Kyoto Fu","22","Kyoto Shi","1857906","Shimogyo Ku","26106","34.95","135.8167","1"],"600-8098":["JP","600-8098","Inaricho","Kyoto Fu","22","Kyoto Shi","1857906","Shimogyo Ku","26106","34.95","135.8167","1"],"600-8099":["JP","600-8099","Kamiyanagicho","Kyoto Fu","22","Kyoto Shi","1857906","Shimogyo Ku","26106","34.95","135.8167","1"],"600-8101":["JP","600-8101","Mieidocho","Kyoto Fu","22","Kyoto Shi","1857906","Shimogyo Ku","26106","34.95","135.8167","1"],"600-8102":["JP","600-8102","Hongakujimaecho","Kyoto Fu","22","Kyoto Shi","1857906","Shimogyo Ku","26106","34.95","135.8167","1"],"600-8103":["JP","600-8103","Shiogamacho","Kyoto Fu","22","Kyoto Shi","1857906","Shimogyo Ku","26106","34.95","135.8167","1"],"600-8104":["JP","600-8104","Manjujicho","Kyoto Fu","22","Kyoto Shi","1857906","Shimogyo Ku","26106","34.95","135.8167","1"],"600-8105":["JP","600-8105","Matsuyacho","Kyoto Fu","22","Kyoto Shi","1857906","Shimogyo Ku","26106","34.95","135.8167","1"],"600-8106":["JP","600-8106","Daigocho","Kyoto Fu","22","Kyoto Shi","1857906","Shimogyo Ku","26106","34.9929","135.7505","4"],"600-8107":["JP","600-8107","Higashikazariyacho","Kyoto Fu","22","Kyoto Shi","1857906","Shimogyo Ku","26106","34.95","135.8167","1"],"600-8108":["JP","600-8108","Nishikazariyacho","Kyoto Fu","22","Kyoto Shi","1857906","Shimogyo Ku","26106","34.95","135.8167","1"],"600-8109":["JP","600-8109","Hirayacho","Kyoto Fu","22","Kyoto Shi","1857906","Shimogyo Ku","26106","34.95","135.8167","1"],"600-8110":["JP","600-8110","Minamihashizumecho","Kyoto Fu","22","Kyoto Shi","1857906","Shimogyo Ku","26106","34.95","135.8167","1"],"600-8111":["JP","600-8111","Toichicho","Kyoto Fu","22","Kyoto Shi","1857906","Shimogyo Ku","26106","34.95","135.8167","1"],"600-8112":["JP","600-8112","Yatsuyanagicho","Kyoto Fu","22","Kyoto Shi","1857906","Shimogyo Ku","26106","34.95","135.8167","1"],"600-8113":["JP","600-8113","Hashidonocho","Kyoto Fu","22","Kyoto Shi","1857906","Shimogyo Ku","26106","34.95","135.8167","1"],"600-8114":["JP","600-8114","Hayaocho","Kyoto Fu","22","Kyoto Shi","1857906","Shimogyo Ku","26106","34.95","135.8167","1"],"600-8115":["JP","600-8115","Iwatakicho","Kyoto Fu","22","Kyoto Shi","1857906","Shimogyo Ku","26106","34.95","135.8167","1"],"600-8116":["JP","600-8116","Shoshinjicho","Kyoto Fu","22","Kyoto Shi","1857906","Shimogyo Ku","26106","34.95","135.8167","1"],"600-8117":["JP","600-8117","Minamikyogokucho","Kyoto Fu","22","Kyoto Shi","1857906","Shimogyo Ku","26106","34.95","135.8167","1"],"600-8118":["JP","600-8118","Hiraicho","Kyoto Fu","22","Kyoto Shi","1857906","Shimogyo Ku","26106","34.95","135.8167","1"],"600-8119":["JP","600-8119","Motoshiogamacho","Kyoto Fu","22","Kyoto Shi","1857906","Shimogyo Ku","26106","34.95","135.8167","1"],"600-8120":["JP","600-8120","Wakamiyacho","Kyoto Fu","22","Kyoto Shi","1857906","Shimogyo Ku","26106","34.95","135.8167","1"],"600-8121":["JP","600-8121","Kikuyacho","Kyoto Fu","22","Kyoto Shi","1857906","Shimogyo Ku","26106","34.95","135.8167","1"],"600-8122":["JP","600-8122","Hiraokacho","Kyoto Fu","22","Kyoto Shi","1857906","Shimogyo Ku","26106","34.95","135.8167","1"],"600-8123":["JP","600-8123","Takamiyacho","Kyoto Fu","22","Kyoto Shi","1857906","Shimogyo Ku","26106","34.95","135.8167","1"],"600-8124":["JP","600-8124","Tomimatsucho","Kyoto Fu","22","Kyoto Shi","1857906","Shimogyo Ku","26106","34.95","135.8167","1"],"600-8125":["JP","600-8125","Tomihamacho","Kyoto Fu","22","Kyoto Shi","1857906","Shimogyo Ku","26106","34.95","135.8167","1"],"600-8126":["JP","600-8126","Kagiyacho","Kyoto Fu","22","Kyoto Shi","1857906","Shimogyo Ku","26106","34.95","135.8167","1"],"600-8127":["JP","600-8127","Umeminatocho","Kyoto Fu","22","Kyoto Shi","1857906","Shimogyo Ku","26106","34.95","135.8167","1"],"600-8128":["JP","600-8128","Daikucho","Kyoto Fu","22","Kyoto Shi","1857906","Shimogyo Ku","26106","34.95","135.8167","1"],"600-8129":["JP","600-8129","Tameikecho","Kyoto Fu","22","Kyoto Shi","1857906","Shimogyo Ku","26106","34.95","135.8167","1"],"600-8130":["JP","600-8130","Konyacho","Kyoto Fu","22","Kyoto Shi","1857906","Shimogyo Ku","26106","34.95","135.8167","1"],"600-8131":["JP","600-8131","Kamininomiyacho","Kyoto Fu","22","Kyoto Shi","1857906","Shimogyo Ku","26106","34.95","135.8167","1"],"600-8132":["JP","600-8132","Shimoninomiyacho","Kyoto Fu","22","Kyoto Shi","1857906","Shimogyo Ku","26106","34.95","135.8167","1"],"600-8133":["JP","600-8133","Inaricho(Shichijodorikamogawasujini","Kyoto Fu","22","Kyoto Shi","1857906","Shimogyo Ku","26106","34.95","135.8167","1"],"600-8134":["JP","600-8134","Sannocho","Kyoto Fu","22","Kyoto Shi","1857906","Shimogyo Ku","26106","34.95","135.8167","1"],"600-8135":["JP","600-8135","Kamisannomiyacho","Kyoto Fu","22","Kyoto Shi","1857906","Shimogyo Ku","26106","34.95","135.8167","1"],"600-8136":["JP","600-8136","Shimosannomiyacho","Kyoto Fu","22","Kyoto Shi","1857906","Shimogyo Ku","26106","34.95","135.8167","1"],"600-8137":["JP","600-8137","Juzenjicho","Kyoto Fu","22","Kyoto Shi","1857906","Shimogyo Ku","26106","34.95","135.8167","1"],"600-8138":["JP","600-8138","Omiyacho","Kyoto Fu","22","Kyoto Shi","1857906","Shimogyo Ku","26106","34.95","135.8167","1"],"600-8139":["JP","600-8139","Hachiojicho","Kyoto Fu","22","Kyoto Shi","1857906","Shimogyo Ku","26106","34.95","135.8167","1"],"600-8141":["JP","600-8141","Shinhiyoshicho","Kyoto Fu","22","Kyoto Shi","1857906","Shimogyo Ku","26106","34.95","135.8167","1"],"600-8142":["JP","600-8142","Nayacho","Kyoto Fu","22","Kyoto Shi","1857906","Shimogyo Ku","26106","34.95","135.8167","1"],"600-8143":["JP","600-8143","Sumiyoshicho","Kyoto Fu","22","Kyoto Shi","1857906","Shimogyo Ku","26106","34.95","135.8167","1"],"600-8144":["JP","600-8144","Shioyacho","Kyoto Fu","22","Kyoto Shi","1857906","Shimogyo Ku","26106","34.95","135.8167","1"],"600-8145":["JP","600-8145","Kaizancho","Kyoto Fu","22","Kyoto Shi","1857906","Shimogyo Ku","26106","34.95","135.8167","1"],"600-8146":["JP","600-8146","Zaimokucho","Kyoto Fu","22","Kyoto Shi","1857906","Shimogyo Ku","26106","34.95","135.8167","1"],"600-8147":["JP","600-8147","Horizumecho","Kyoto Fu","22","Kyoto Shi","1857906","Shimogyo Ku","26106","34.95","135.8167","1"],"600-8148":["JP","600-8148","Ameyacho","Kyoto Fu","22","Kyoto Shi","1857906","Shimogyo Ku","26106","34.95","135.8167","1"],"600-8149":["JP","600-8149","Kogawacho","Kyoto Fu","22","Kyoto Shi","1857906","Shimogyo Ku","26106","34.95","135.8167","1"],"600-8150":["JP","600-8150","Kamijuzuyacho","Kyoto Fu","22","Kyoto Shi","1857906","Shimogyo Ku","26106","34.95","135.8167","1"],"600-8151":["JP","600-8151","Uchikoshicho","Kyoto Fu","22","Kyoto Shi","1857906","Shimogyo Ku","26106","34.95","135.8167","1"],"600-8152":["JP","600-8152","Tsutsuganecho","Kyoto Fu","22","Kyoto Shi","1857906","Shimogyo Ku","26106","34.95","135.8167","1"],"600-8153":["JP","600-8153","Nijuninkocho","Kyoto Fu","22","Kyoto Shi","1857906","Shimogyo Ku","26106","34.95","135.8167","1"],"600-8154":["JP","600-8154","Enokicho","Kyoto Fu","22","Kyoto Shi","1857906","Shimogyo Ku","26106","34.95","135.8167","1"],"600-8155":["JP","600-8155","Nishitamamizucho","Kyoto Fu","22","Kyoto Shi","1857906","Shimogyo Ku","26106","34.95","135.8167","1"],"600-8156":["JP","600-8156","Sasayacho","Kyoto Fu","22","Kyoto Shi","1857906","Shimogyo Ku","26106","34.95","135.8167","1"],"600-8157":["JP","600-8157","Tachibanacho","Kyoto Fu","22","Kyoto Shi","1857906","Shimogyo Ku","26106","34.95","135.8167","1"],"600-8158":["JP","600-8158","Shokuyacho","Kyoto Fu","22","Kyoto Shi","1857906","Shimogyo Ku","26106","34.95","135.8167","1"],"600-8159":["JP","600-8159","Kamemachi","Kyoto Fu","22","Kyoto Shi","1857906","Shimogyo Ku","26106","34.95","135.8167","1"],"600-8160":["JP","600-8160","Nishiuoyacho","Kyoto Fu","22","Kyoto Shi","1857906","Shimogyo Ku","26106","34.95","135.8167","1"],"600-8161":["JP","600-8161","Daikokucho","Kyoto Fu","22","Kyoto Shi","1857906","Shimogyo Ku","26106","34.95","135.8167","1"],"600-8162":["JP","600-8162","Sakaicho","Kyoto Fu","22","Kyoto Shi","1857906","Shimogyo Ku","26106","34.95","135.8167","1"],"600-8163":["JP","600-8163","Shimosuwancho","Kyoto Fu","22","Kyoto Shi","1857906","Shimogyo Ku","26106","34.95","135.8167","1"],"600-8164":["JP","600-8164","Kamiyanagicho","Kyoto Fu","22","Kyoto Shi","1857906","Shimogyo Ku","26106","34.95","135.8167","1"],"600-8165":["JP","600-8165","Shimoyanagicho","Kyoto Fu","22","Kyoto Shi","1857906","Shimogyo Ku","26106","34.95","135.8167","1"],"600-8166":["JP","600-8166","Inuicho","Kyoto Fu","22","Kyoto Shi","1857906","Shimogyo Ku","26106","34.95","135.8167","1"],"600-8167":["JP","600-8167","Tokiwacho","Kyoto Fu","22","Kyoto Shi","1857906","Shimogyo Ku","26106","34.95","135.8167","1"],"600-8168":["JP","600-8168","Yaoyacho","Kyoto Fu","22","Kyoto Shi","1857906","Shimogyo Ku","26106","34.95","135.8167","1"],"600-8169":["JP","600-8169","Higashiuoyacho","Kyoto Fu","22","Kyoto Shi","1857906","Shimogyo Ku","26106","34.95","135.8167","1"],"600-8170":["JP","600-8170","Kamisuwancho","Kyoto Fu","22","Kyoto Shi","1857906","Shimogyo Ku","26106","34.95","135.8167","1"],"600-8171":["JP","600-8171","Kamihiranocho","Kyoto Fu","22","Kyoto Shi","1857906","Shimogyo Ku","26106","34.95","135.8167","1"],"600-8172":["JP","600-8172","Shimohiranocho","Kyoto Fu","22","Kyoto Shi","1857906","Shimogyo Ku","26106","34.95","135.8167","1"],"600-8173":["JP","600-8173","Butsuguyacho","Kyoto Fu","22","Kyoto Shi","1857906","Shimogyo Ku","26106","34.95","135.8167","1"],"600-8174":["JP","600-8174","Takatsukicho","Kyoto Fu","22","Kyoto Shi","1857906","Shimogyo Ku","26106","34.95","135.8167","1"],"600-8175":["JP","600-8175","Karasuma(2-Chome)","Kyoto Fu","22","Kyoto Shi","1857906","Shimogyo Ku","26106","34.95","135.8167","1"],"600-8176":["JP","600-8176","Kitamachi","Kyoto Fu","22","Kyoto Shi","1857906","Shimogyo Ku","26106","34.95","135.8167","1"],"600-8177":["JP","600-8177","Osakacho","Kyoto Fu","22","Kyoto Shi","1857906","Shimogyo Ku","26106","34.95","135.8167","1"],"600-8178":["JP","600-8178","Kagiyacho","Kyoto Fu","22","Kyoto Shi","1857906","Shimogyo Ku","26106","34.95","135.8167","1"],"600-8179":["JP","600-8179","Yokosuwancho","Kyoto Fu","22","Kyoto Shi","1857906","Shimogyo Ku","26106","34.95","135.8167","1"],"600-8180":["JP","600-8180","Shimomanjujicho","Kyoto Fu","22","Kyoto Shi","1857906","Shimogyo Ku","26106","34.95","135.8167","1"],"600-8181":["JP","600-8181","Otsucho","Kyoto Fu","22","Kyoto Shi","1857906","Shimogyo Ku","26106","34.95","135.8167","1"],"600-8182":["JP","600-8182","Nushiyacho","Kyoto Fu","22","Kyoto Shi","1857906","Shimogyo Ku","26106","34.95","135.8167","1"],"600-8183":["JP","600-8183","Ebisunocho","Kyoto Fu","22","Kyoto Shi","1857906","Shimogyo Ku","26106","34.95","135.8167","1"],"600-8184":["JP","600-8184","Tenjincho","Kyoto Fu","22","Kyoto Shi","1857906","Shimogyo Ku","26106","34.95","135.8167","1"],"600-8185":["JP","600-8185","Hanayacho","Kyoto Fu","22","Kyoto Shi","1857906","Shimogyo Ku","26106","34.95","135.8167","1"],"600-8186":["JP","600-8186","Tomitacho","Kyoto Fu","22","Kyoto Shi","1857906","Shimogyo Ku","26106","34.95","135.8167","1"],"600-8187":["JP","600-8187","Hashizumecho","Kyoto Fu","22","Kyoto Shi","1857906","Shimogyo Ku","26106","34.95","135.8167","1"],"600-8188":["JP","600-8188","Izumicho","Kyoto Fu","22","Kyoto Shi","1857906","Shimogyo Ku","26106","34.95","135.8167","1"],"600-8189":["JP","600-8189","Fukushimacho","Kyoto Fu","22","Kyoto Shi","1857906","Shimogyo Ku","26106","34.95","135.8167","1"],"600-8190":["JP","600-8190","Higashitamamizucho","Kyoto Fu","22","Kyoto Shi","1857906","Shimogyo Ku","26106","34.95","135.8167","1"],"600-8191":["JP","600-8191","Sakaimachi(Gojodoritakakuranishiiru","Kyoto Fu","22","Kyoto Shi","1857906","Shimogyo Ku","26106","34.95","135.8167","1"],"600-8192":["JP","600-8192","Tomiyacho","Kyoto Fu","22","Kyoto Shi","1857906","Shimogyo Ku","26106","34.95","135.8167","1"],"600-8193":["JP","600-8193","Honeyacho(Rokujodoritakakurahigashi","Kyoto Fu","22","Kyoto Shi","1857906","Shimogyo Ku","26106","34.95","135.8167","1"],"600-8194":["JP","600-8194","Sakaecho","Kyoto Fu","22","Kyoto Shi","1857906","Shimogyo Ku","26106","34.95","135.8167","1"],"600-8195":["JP","600-8195","Masuyacho","Kyoto Fu","22","Kyoto Shi","1857906","Shimogyo Ku","26106","34.95","135.8167","1"],"600-8196":["JP","600-8196","Hachikencho","Kyoto Fu","22","Kyoto Shi","1857906","Shimogyo Ku","26106","34.95","135.8167","1"],"600-8197":["JP","600-8197","Karamonocho","Kyoto Fu","22","Kyoto Shi","1857906","Shimogyo Ku","26106","34.95","135.8167","1"],"600-8198":["JP","600-8198","Wakamatsucho","Kyoto Fu","22","Kyoto Shi","1857906","Shimogyo Ku","26106","34.95","135.8167","1"],"600-8199":["JP","600-8199","Yorozuyacho","Kyoto Fu","22","Kyoto Shi","1857906","Shimogyo Ku","26106","34.95","135.8167","1"],"600-8201":["JP","600-8201","Wakamiyacho","Kyoto Fu","22","Kyoto Shi","1857906","Shimogyo Ku","26106","34.95","135.8167","1"],"600-8202":["JP","600-8202","Kawabatacho(Sonota)","Kyoto Fu","22","Kyoto Shi","1857906","Shimogyo Ku","26106","34.95","135.8167","1"],"600-8203":["JP","600-8203","Yakatacho","Kyoto Fu","22","Kyoto Shi","1857906","Shimogyo Ku","26106","34.95","135.8167","1"],"600-8204":["JP","600-8204","Higashinocho","Kyoto Fu","22","Kyoto Shi","1857906","Shimogyo Ku","26106","34.95","135.8167","1"],"600-8205":["JP","600-8205","Nishinocho","Kyoto Fu","22","Kyoto Shi","1857906","Shimogyo Ku","26106","34.95","135.8167","1"],"600-8206":["JP","600-8206","Shimonocho","Kyoto Fu","22","Kyoto Shi","1857906","Shimogyo Ku","26106","34.95","135.8167","1"],"600-8207":["JP","600-8207","Kaminocho(Sonota)","Kyoto Fu","22","Kyoto Shi","1857906","Shimogyo Ku","26106","34.95","135.8167","1"],"600-8208":["JP","600-8208","Koinaricho","Kyoto Fu","22","Kyoto Shi","1857906","Shimogyo Ku","26106","34.95","135.8167","1"],"600-8209":["JP","600-8209","Gonocho","Kyoto Fu","22","Kyoto Shi","1857906","Shimogyo Ku","26106","34.95","135.8167","1"],"600-8210":["JP","600-8210","Sakuragicho","Kyoto Fu","22","Kyoto Shi","1857906","Shimogyo Ku","26106","34.95","135.8167","1"],"600-8211":["JP","600-8211","Maoyacho","Kyoto Fu","22","Kyoto Shi","1857906","Shimogyo Ku","26106","34.95","135.8167","1"],"600-8212":["JP","600-8212","Shiokojicho","Kyoto Fu","22","Kyoto Shi","1857906","Shimogyo Ku","26106","34.95","135.8167","1"],"600-8213":["JP","600-8213","Higashishiokoji Mukaihatacho","Kyoto Fu","22","Kyoto Shi","1857906","Shimogyo Ku","26106","34.95","135.8167","1"],"600-8214":["JP","600-8214","Higashishiokoji Takakuracho","Kyoto Fu","22","Kyoto Shi","1857906","Shimogyo Ku","26106","34.95","135.8167","1"],"600-8215":["JP","600-8215","Higashishiokoji Kamadonocho","Kyoto Fu","22","Kyoto Shi","1857906","Shimogyo Ku","26106","34.95","135.8167","1"],"600-8216":["JP","600-8216","Higashishiokojicho","Kyoto Fu","22","Kyoto Shi","1857906","Shimogyo Ku","26106","34.95","135.8167","1"],"600-8217":["JP","600-8217","Higashisakaicho","Kyoto Fu","22","Kyoto Shi","1857906","Shimogyo Ku","26106","34.95","135.8167","1"],"600-8218":["JP","600-8218","Nishisakaicho","Kyoto Fu","22","Kyoto Shi","1857906","Shimogyo Ku","26106","34.95","135.8167","1"],"600-8219":["JP","600-8219","Nakaicho","Kyoto Fu","22","Kyoto Shi","1857906","Shimogyo Ku","26106","34.95","135.8167","1"],"600-8221":["JP","600-8221","Takaocho","Kyoto Fu","22","Kyoto Shi","1857906","Shimogyo Ku","26106","34.95","135.8167","1"],"600-8222":["JP","600-8222","Mongakucho","Kyoto Fu","22","Kyoto Shi","1857906","Shimogyo Ku","26106","34.95","135.8167","1"],"600-8223":["JP","600-8223","Daikokucho","Kyoto Fu","22","Kyoto Shi","1857906","Shimogyo Ku","26106","34.95","135.8167","1"],"600-8224":["JP","600-8224","Higashicho","Kyoto Fu","22","Kyoto Shi","1857906","Shimogyo Ku","26106","34.95","135.8167","1"],"600-8225":["JP","600-8225","Higashidaikucho","Kyoto Fu","22","Kyoto Shi","1857906","Shimogyo Ku","26106","34.95","135.8167","1"],"600-8226":["JP","600-8226","Tsuchihashicho","Kyoto Fu","22","Kyoto Shi","1857906","Shimogyo Ku","26106","34.95","135.8167","1"],"600-8227":["JP","600-8227","Hishiyacho","Kyoto Fu","22","Kyoto Shi","1857906","Shimogyo Ku","26106","34.95","135.8167","1"],"600-8228":["JP","600-8228","Kitakojicho","Kyoto Fu","22","Kyoto Shi","1857906","Shimogyo Ku","26106","34.95","135.8167","1"],"600-8229":["JP","600-8229","Komeyacho","Kyoto Fu","22","Kyoto Shi","1857906","Shimogyo Ku","26106","34.95","135.8167","1"],"600-8231":["JP","600-8231","Aburanokojicho","Kyoto Fu","22","Kyoto Shi","1857906","Shimogyo Ku","26106","34.95","135.8167","1"],"600-8232":["JP","600-8232","Minamimachi","Kyoto Fu","22","Kyoto Shi","1857906","Shimogyo Ku","26106","34.95","135.8167","1"],"600-8233":["JP","600-8233","Kitafudondocho","Kyoto Fu","22","Kyoto Shi","1857906","Shimogyo Ku","26106","34.95","135.8167","1"],"600-8234":["JP","600-8234","Minamifudondocho","Kyoto Fu","22","Kyoto Shi","1857906","Shimogyo Ku","26106","34.95","135.8167","1"],"600-8235":["JP","600-8235","Higashiaburanokojicho","Kyoto Fu","22","Kyoto Shi","1857906","Shimogyo Ku","26106","34.95","135.8167","1"],"600-8236":["JP","600-8236","Nishiaburanokojicho","Kyoto Fu","22","Kyoto Shi","1857906","Shimogyo Ku","26106","34.95","135.8167","1"],"600-8237":["JP","600-8237","Taimatsucho","Kyoto Fu","22","Kyoto Shi","1857906","Shimogyo Ku","26106","34.95","135.8167","1"],"600-8238":["JP","600-8238","Mikatakonyacho","Kyoto Fu","22","Kyoto Shi","1857906","Shimogyo Ku","26106","34.95","135.8167","1"],"600-8239":["JP","600-8239","Kamayacho","Kyoto Fu","22","Kyoto Shi","1857906","Shimogyo Ku","26106","34.95","135.8167","1"],"600-8241":["JP","600-8241","Shimizucho","Kyoto Fu","22","Kyoto Shi","1857906","Shimogyo Ku","26106","34.95","135.8167","1"],"600-8242":["JP","600-8242","Kamiebisucho","Kyoto Fu","22","Kyoto Shi","1857906","Shimogyo Ku","26106","34.95","135.8167","1"],"600-8243":["JP","600-8243","Minamiebisucho","Kyoto Fu","22","Kyoto Shi","1857906","Shimogyo Ku","26106","34.95","135.8167","1"],"600-8244":["JP","600-8244","Bomonnakanocho","Kyoto Fu","22","Kyoto Shi","1857906","Shimogyo Ku","26106","34.95","135.8167","1"],"600-8245":["JP","600-8245","Furuotabicho","Kyoto Fu","22","Kyoto Shi","1857906","Shimogyo Ku","26106","34.95","135.8167","1"],"600-8246":["JP","600-8246","Kakigauchicho","Kyoto Fu","22","Kyoto Shi","1857906","Shimogyo Ku","26106","34.95","135.8167","1"],"600-8247":["JP","600-8247","Hachijobomoncho(Shiokojidorikuromon","Kyoto Fu","22","Kyoto Shi","1857906","Shimogyo Ku","26106","34.95","135.8167","1"],"600-8248":["JP","600-8248","Kaminakanocho","Kyoto Fu","22","Kyoto Shi","1857906","Shimogyo Ku","26106","34.95","135.8167","1"],"600-8249":["JP","600-8249","Shimokojiyacho","Kyoto Fu","22","Kyoto Shi","1857906","Shimogyo Ku","26106","34.95","135.8167","1"],"600-8251":["JP","600-8251","Minamiyaoyacho","Kyoto Fu","22","Kyoto Shi","1857906","Shimogyo Ku","26106","34.95","135.8167","1"],"600-8252":["JP","600-8252","Kawabatacho(Kizuyabashidorihorikawa","Kyoto Fu","22","Kyoto Shi","1857906","Shimogyo Ku","26106","34.95","135.8167","1"],"600-8253":["JP","600-8253","Kizuyacho","Kyoto Fu","22","Kyoto Shi","1857906","Shimogyo Ku","26106","34.95","135.8167","1"],"600-8254":["JP","600-8254","Isematsucho","Kyoto Fu","22","Kyoto Shi","1857906","Shimogyo Ku","26106","34.95","135.8167","1"],"600-8255":["JP","600-8255","Shimizucho","Kyoto Fu","22","Kyoto Shi","1857906","Shimogyo Ku","26106","34.95","135.8167","1"],"600-8256":["JP","600-8256","Matsumotocho(Iwagamidorikizuyabashi","Kyoto Fu","22","Kyoto Shi","1857906","Shimogyo Ku","26106","34.95","135.8167","1"],"600-8257":["JP","600-8257","Sangengaechicho","Kyoto Fu","22","Kyoto Shi","1857906","Shimogyo Ku","26106","34.95","135.8167","1"],"600-8258":["JP","600-8258","Kanegaecho","Kyoto Fu","22","Kyoto Shi","1857906","Shimogyo Ku","26106","34.95","135.8167","1"],"600-8259":["JP","600-8259","Kamikojiyacho","Kyoto Fu","22","Kyoto Shi","1857906","Shimogyo Ku","26106","34.95","135.8167","1"],"600-8261":["JP","600-8261","Hanazonocho","Kyoto Fu","22","Kyoto Shi","1857906","Shimogyo Ku","26106","34.95","135.8167","1"],"600-8262":["JP","600-8262","Yaoyacho","Kyoto Fu","22","Kyoto Shi","1857906","Shimogyo Ku","26106","34.95","135.8167","1"],"600-8263":["JP","600-8263","Shimoonotana(4-Chome)","Kyoto Fu","22","Kyoto Shi","1857906","Shimogyo Ku","26106","34.95","135.8167","1"],"600-8264":["JP","600-8264","Taruyacho","Kyoto Fu","22","Kyoto Shi","1857906","Shimogyo Ku","26106","34.95","135.8167","1"],"600-8265":["JP","600-8265","Teppocho","Kyoto Fu","22","Kyoto Shi","1857906","Shimogyo Ku","26106","34.95","135.8167","1"],"600-8266":["JP","600-8266","Kaminocho","Kyoto Fu","22","Kyoto Shi","1857906","Shimogyo Ku","26106","34.95","135.8167","1"],"600-8267":["JP","600-8267","Gokiyacho","Kyoto Fu","22","Kyoto Shi","1857906","Shimogyo Ku","26106","34.95","135.8167","1"],"600-8268":["JP","600-8268","Daikucho","Kyoto Fu","22","Kyoto Shi","1857906","Shimogyo Ku","26106","34.95","135.8167","1"],"600-8269":["JP","600-8269","Nishiyaoyacho","Kyoto Fu","22","Kyoto Shi","1857906","Shimogyo Ku","26106","34.95","135.8167","1"],"600-8301":["JP","600-8301","Kamiyanagicho","Kyoto Fu","22","Kyoto Shi","1857906","Shimogyo Ku","26106","34.95","135.8167","1"],"600-8302":["JP","600-8302","Ebisucho","Kyoto Fu","22","Kyoto Shi","1857906","Shimogyo Ku","26106","34.95","135.8167","1"],"600-8303":["JP","600-8303","Zeniyacho","Kyoto Fu","22","Kyoto Shi","1857906","Shimogyo Ku","26106","34.95","135.8167","1"],"600-8304":["JP","600-8304","Ushitoracho","Kyoto Fu","22","Kyoto Shi","1857906","Shimogyo Ku","26106","34.95","135.8167","1"],"600-8305":["JP","600-8305","Higashiwakamatsucho","Kyoto Fu","22","Kyoto Shi","1857906","Shimogyo Ku","26106","34.95","135.8167","1"],"600-8306":["JP","600-8306","Hiranocho","Kyoto Fu","22","Kyoto Shi","1857906","Shimogyo Ku","26106","34.95","135.8167","1"],"600-8307":["JP","600-8307","Tatsumicho","Kyoto Fu","22","Kyoto Shi","1857906","Shimogyo Ku","26106","34.95","135.8167","1"],"600-8308":["JP","600-8308","Atarashicho","Kyoto Fu","22","Kyoto Shi","1857906","Shimogyo Ku","26106","34.95","135.8167","1"],"600-8310":["JP","600-8310","Ebisunocho","Kyoto Fu","22","Kyoto Shi","1857906","Shimogyo Ku","26106","34.95","135.8167","1"],"600-8311":["JP","600-8311","Bishamoncho","Kyoto Fu","22","Kyoto Shi","1857906","Shimogyo Ku","26106","34.95","135.8167","1"],"600-8312":["JP","600-8312","Kamisuzuyacho","Kyoto Fu","22","Kyoto Shi","1857906","Shimogyo Ku","26106","34.95","135.8167","1"],"600-8313":["JP","600-8313","Kamiwakamiyacho","Kyoto Fu","22","Kyoto Shi","1857906","Shimogyo Ku","26106","34.95","135.8167","1"],"600-8314":["JP","600-8314","Wakamiyacho","Kyoto Fu","22","Kyoto Shi","1857906","Shimogyo Ku","26106","34.95","135.8167","1"],"600-8315":["JP","600-8315","Higashimatsuyacho","Kyoto Fu","22","Kyoto Shi","1857906","Shimogyo Ku","26106","34.95","135.8167","1"],"600-8316":["JP","600-8316","Shihommatsucho","Kyoto Fu","22","Kyoto Shi","1857906","Shimogyo Ku","26106","34.95","135.8167","1"],"600-8317":["JP","600-8317","Kagiyacho","Kyoto Fu","22","Kyoto Shi","1857906","Shimogyo Ku","26106","34.95","135.8167","1"],"600-8318":["JP","600-8318","Izutsucho","Kyoto Fu","22","Kyoto Shi","1857906","Shimogyo Ku","26106","34.95","135.8167","1"],"600-8319":["JP","600-8319","Takeyacho(Wakamiyadorikitakojisagar","Kyoto Fu","22","Kyoto Shi","1857906","Shimogyo Ku","26106","34.95","135.8167","1"],"600-8320":["JP","600-8320","Fukumotocho","Kyoto Fu","22","Kyoto Shi","1857906","Shimogyo Ku","26106","34.95","135.8167","1"],"600-8321":["JP","600-8321","Yaoyacho","Kyoto Fu","22","Kyoto Shi","1857906","Shimogyo Ku","26106","34.95","135.8167","1"],"600-8322":["JP","600-8322","Koyanagicho","Kyoto Fu","22","Kyoto Shi","1857906","Shimogyo Ku","26106","34.95","135.8167","1"],"600-8323":["JP","600-8323","Kanayacho","Kyoto Fu","22","Kyoto Shi","1857906","Shimogyo Ku","26106","34.95","135.8167","1"],"600-8324":["JP","600-8324","Higashigawacho","Kyoto Fu","22","Kyoto Shi","1857906","Shimogyo Ku","26106","34.95","135.8167","1"],"600-8325":["JP","600-8325","Nishigawacho","Kyoto Fu","22","Kyoto Shi","1857906","Shimogyo Ku","26106","34.95","135.8167","1"],"600-8326":["JP","600-8326","Nishimatsuyacho","Kyoto Fu","22","Kyoto Shi","1857906","Shimogyo Ku","26106","34.95","135.8167","1"],"600-8327":["JP","600-8327","Nishinotoincho","Kyoto Fu","22","Kyoto Shi","1857906","Shimogyo Ku","26106","34.95","135.8167","1"],"600-8328":["JP","600-8328","Ebisumizucho","Kyoto Fu","22","Kyoto Shi","1857906","Shimogyo Ku","26106","34.95","135.8167","1"],"600-8329":["JP","600-8329","Kajiyacho","Kyoto Fu","22","Kyoto Shi","1857906","Shimogyo Ku","26106","34.95","135.8167","1"],"600-8331":["JP","600-8331","Kintoyokocho","Kyoto Fu","22","Kyoto Shi","1857906","Shimogyo Ku","26106","34.95","135.8167","1"],"600-8332":["JP","600-8332","Nakakanabutsucho","Kyoto Fu","22","Kyoto Shi","1857906","Shimogyo Ku","26106","34.95","135.8167","1"],"600-8333":["JP","600-8333","Bokumikanabutsucho","Kyoto Fu","22","Kyoto Shi","1857906","Shimogyo Ku","26106","34.95","135.8167","1"],"600-8334":["JP","600-8334","Nishiwakamatsucho","Kyoto Fu","22","Kyoto Shi","1857906","Shimogyo Ku","26106","34.95","135.8167","1"],"600-8335":["JP","600-8335","Sumiyoshicho(Samegaidoritakatsujisa","Kyoto Fu","22","Kyoto Shi","1857906","Shimogyo Ku","26106","34.95","135.8167","1"],"600-8336":["JP","600-8336","Ganjitsucho","Kyoto Fu","22","Kyoto Shi","1857906","Shimogyo Ku","26106","34.95","135.8167","1"],"600-8337":["JP","600-8337","Samegaicho","Kyoto Fu","22","Kyoto Shi","1857906","Shimogyo Ku","26106","34.95","135.8167","1"],"600-8338":["JP","600-8338","Sensuicho","Kyoto Fu","22","Kyoto Shi","1857906","Shimogyo Ku","26106","34.95","135.8167","1"],"600-8340":["JP","600-8340","Hanayacho(Hanayachodoriaburanokojin","Kyoto Fu","22","Kyoto Shi","1857906","Shimogyo Ku","26106","34.95","135.8167","1"],"600-8341":["JP","600-8341","Gakurincho","Kyoto Fu","22","Kyoto Shi","1857906","Shimogyo Ku","26106","34.95","135.8167","1"],"600-8342":["JP","600-8342","Yamakawacho","Kyoto Fu","22","Kyoto Shi","1857906","Shimogyo Ku","26106","34.95","135.8167","1"],"600-8343":["JP","600-8343","Uematsucho(Shomendorinishinotoinnis","Kyoto Fu","22","Kyoto Shi","1857906","Shimogyo Ku","26106","34.95","135.8167","1"],"600-8344":["JP","600-8344","Yanagicho","Kyoto Fu","22","Kyoto Shi","1857906","Shimogyo Ku","26106","34.95","135.8167","1"],"600-8345":["JP","600-8345","Momijicho","Kyoto Fu","22","Kyoto Shi","1857906","Shimogyo Ku","26106","34.95","135.8167","1"],"600-8346":["JP","600-8346","Tamamotocho","Kyoto Fu","22","Kyoto Shi","1857906","Shimogyo Ku","26106","34.95","135.8167","1"],"600-8347":["JP","600-8347","Butsuguyacho","Kyoto Fu","22","Kyoto Shi","1857906","Shimogyo Ku","26106","34.95","135.8167","1"],"600-8348":["JP","600-8348","Juzuyacho","Kyoto Fu","22","Kyoto Shi","1857906","Shimogyo Ku","26106","34.95","135.8167","1"],"600-8349":["JP","600-8349","Sakaicho","Kyoto Fu","22","Kyoto Shi","1857906","Shimogyo Ku","26106","34.95","135.8167","1"],"600-8351":["JP","600-8351","Tominagacho","Kyoto Fu","22","Kyoto Shi","1857906","Shimogyo Ku","26106","34.95","135.8167","1"],"600-8352":["JP","600-8352","Kichimonjicho(Iwagamidorimatsubaraa","Kyoto Fu","22","Kyoto Shi","1857906","Shimogyo Ku","26106","34.95","135.8167","1"],"600-8353":["JP","600-8353","Takatsuji Inokumacho","Kyoto Fu","22","Kyoto Shi","1857906","Shimogyo Ku","26106","34.95","135.8167","1"],"600-8354":["JP","600-8354","Jumonjicho","Kyoto Fu","22","Kyoto Shi","1857906","Shimogyo Ku","26106","34.95","135.8167","1"],"600-8355":["JP","600-8355","Raikodocho","Kyoto Fu","22","Kyoto Shi","1857906","Shimogyo Ku","26106","34.95","135.8167","1"],"600-8356":["JP","600-8356","Kitamonzencho","Kyoto Fu","22","Kyoto Shi","1857906","Shimogyo Ku","26106","34.95","135.8167","1"],"600-8357":["JP","600-8357","Kakimotocho","Kyoto Fu","22","Kyoto Shi","1857906","Shimogyo Ku","26106","34.95","135.8167","1"],"600-8358":["JP","600-8358","Monzencho","Kyoto Fu","22","Kyoto Shi","1857906","Shimogyo Ku","26106","34.95","135.8167","1"],"600-8359":["JP","600-8359","Maruyacho","Kyoto Fu","22","Kyoto Shi","1857906","Shimogyo Ku","26106","34.95","135.8167","1"],"600-8361":["JP","600-8361","Horinogamicho","Kyoto Fu","22","Kyoto Shi","1857906","Shimogyo Ku","26106","34.95","135.8167","1"],"600-8362":["JP","600-8362","Chudoji Maecho","Kyoto Fu","22","Kyoto Shi","1857906","Shimogyo Ku","26106","34.95","135.8167","1"],"600-8363":["JP","600-8363","Omiya(1-3-Chome)","Kyoto Fu","22","Kyoto Shi","1857906","Shimogyo Ku","26106","34.95","135.8167","1"],"600-8364":["JP","600-8364","Tsukinuke(Chome)","Kyoto Fu","22","Kyoto Shi","1857906","Shimogyo Ku","26106","34.95","135.8167","1"],"600-8365":["JP","600-8365","Tambakaidocho","Kyoto Fu","22","Kyoto Shi","1857906","Shimogyo Ku","26106","34.95","135.8167","1"],"600-8371":["JP","600-8371","Nishimonzencho","Kyoto Fu","22","Kyoto Shi","1857906","Shimogyo Ku","26106","34.95","135.8167","1"],"600-8372":["JP","600-8372","Minamimonzencho","Kyoto Fu","22","Kyoto Shi","1857906","Shimogyo Ku","26106","34.95","135.8167","1"],"600-8373":["JP","600-8373","Shimogojocho","Kyoto Fu","22","Kyoto Shi","1857906","Shimogyo Ku","26106","34.95","135.8167","1"],"600-8374":["JP","600-8374","Yabunochicho","Kyoto Fu","22","Kyoto Shi","1857906","Shimogyo Ku","26106","34.95","135.8167","1"],"600-8375":["JP","600-8375","Shimochofukujicho","Kyoto Fu","22","Kyoto Shi","1857906","Shimogyo Ku","26106","34.95","135.8167","1"],"600-8376":["JP","600-8376","Kamichofukujicho","Kyoto Fu","22","Kyoto Shi","1857906","Shimogyo Ku","26106","34.95","135.8167","1"],"600-8377":["JP","600-8377","Kamigojocho","Kyoto Fu","22","Kyoto Shi","1857906","Shimogyo Ku","26106","34.95","135.8167","1"],"600-8381":["JP","600-8381","Sagarimatsucho","Kyoto Fu","22","Kyoto Shi","1857906","Shimogyo Ku","26106","34.95","135.8167","1"],"600-8382":["JP","600-8382","Shioyacho(Kuromondoriayanokojisagar","Kyoto Fu","22","Kyoto Shi","1857906","Shimogyo Ku","26106","34.95","135.8167","1"],"600-8383":["JP","600-8383","Ayaomiyacho","Kyoto Fu","22","Kyoto Shi","1857906","Shimogyo Ku","26106","34.95","135.8167","1"],"600-8384":["JP","600-8384","Imadaikokucho","Kyoto Fu","22","Kyoto Shi","1857906","Shimogyo Ku","26106","34.95","135.8167","1"],"600-8385":["JP","600-8385","Goboomiyacho","Kyoto Fu","22","Kyoto Shi","1857906","Shimogyo Ku","26106","34.95","135.8167","1"],"600-8386":["JP","600-8386","Sugiebisucho","Kyoto Fu","22","Kyoto Shi","1857906","Shimogyo Ku","26106","34.95","135.8167","1"],"600-8387":["JP","600-8387","Takatsuji Omiyacho","Kyoto Fu","22","Kyoto Shi","1857906","Shimogyo Ku","26106","34.95","135.8167","1"],"600-8388":["JP","600-8388","Bomoncho","Kyoto Fu","22","Kyoto Shi","1857906","Shimogyo Ku","26106","34.95","135.8167","1"],"600-8389":["JP","600-8389","Shijo Omiyacho","Kyoto Fu","22","Kyoto Shi","1857906","Shimogyo Ku","26106","34.95","135.8167","1"],"600-8390":["JP","600-8390","Matsumotocho","Kyoto Fu","22","Kyoto Shi","1857906","Shimogyo Ku","26106","34.95","135.8167","1"],"600-8391":["JP","600-8391","Satakecho","Kyoto Fu","22","Kyoto Shi","1857906","Shimogyo Ku","26106","34.95","135.8167","1"],"600-8392":["JP","600-8392","Myomanjicho","Kyoto Fu","22","Kyoto Shi","1857906","Shimogyo Ku","26106","34.95","135.8167","1"],"600-8393":["JP","600-8393","Kariganecho(Iwagamidoriayanokojisag","Kyoto Fu","22","Kyoto Shi","1857906","Shimogyo Ku","26106","34.95","135.8167","1"],"600-8394":["JP","600-8394","Sarashiyacho","Kyoto Fu","22","Kyoto Shi","1857906","Shimogyo Ku","26106","34.95","135.8167","1"],"600-8395":["JP","600-8395","Tokuyacho","Kyoto Fu","22","Kyoto Shi","1857906","Shimogyo Ku","26106","34.95","135.8167","1"],"600-8396":["JP","600-8396","Tsuchiyacho","Kyoto Fu","22","Kyoto Shi","1857906","Shimogyo Ku","26106","34.95","135.8167","1"],"600-8397":["JP","600-8397","Nishidacho","Kyoto Fu","22","Kyoto Shi","1857906","Shimogyo Ku","26106","34.95","135.8167","1"],"600-8398":["JP","600-8398","Setoyacho","Kyoto Fu","22","Kyoto Shi","1857906","Shimogyo Ku","26106","34.95","135.8167","1"],"600-8399":["JP","600-8399","Maruyacho","Kyoto Fu","22","Kyoto Shi","1857906","Shimogyo Ku","26106","34.95","135.8167","1"],"600-8401":["JP","600-8401","Torocho","Kyoto Fu","22","Kyoto Shi","1857906","Shimogyo Ku","26106","34.95","135.8167","1"],"600-8402":["JP","600-8402","Oecho","Kyoto Fu","22","Kyoto Shi","1857906","Shimogyo Ku","26106","34.95","135.8167","1"],"600-8403":["JP","600-8403","Yoshimizucho(Akezudorimatsubarasaga","Kyoto Fu","22","Kyoto Shi","1857906","Shimogyo Ku","26106","34.95","135.8167","1"],"600-8404":["JP","600-8404","Fukudenjicho","Kyoto Fu","22","Kyoto Shi","1857906","Shimogyo Ku","26106","34.95","135.8167","1"],"600-8405":["JP","600-8405","Manjujinakanocho","Kyoto Fu","22","Kyoto Shi","1857906","Shimogyo Ku","26106","34.95","135.8167","1"],"600-8406":["JP","600-8406","Kameyacho(Takakuradorigojoagaru.Tak","Kyoto Fu","22","Kyoto Shi","1857906","Shimogyo Ku","26106","34.95","135.8167","1"],"600-8407":["JP","600-8407","Asazumacho","Kyoto Fu","22","Kyoto Shi","1857906","Shimogyo Ku","26106","34.95","135.8167","1"],"600-8408":["JP","600-8408","Fukakusacho","Kyoto Fu","22","Kyoto Shi","1857906","Shimogyo Ku","26106","34.95","135.8167","1"],"600-8409":["JP","600-8409","Tamayacho","Kyoto Fu","22","Kyoto Shi","1857906","Shimogyo Ku","26106","34.95","135.8167","1"],"600-8410":["JP","600-8410","Akuojicho","Kyoto Fu","22","Kyoto Shi","1857906","Shimogyo Ku","26106","34.95","135.8167","1"],"600-8411":["JP","600-8411","Suiginyacho","Kyoto Fu","22","Kyoto Shi","1857906","Shimogyo Ku","26106","34.95","135.8167","1"],"600-8412":["JP","600-8412","Nijohanjikicho","Kyoto Fu","22","Kyoto Shi","1857906","Shimogyo Ku","26106","34.95","135.8167","1"],"600-8413":["JP","600-8413","Omandokorocho","Kyoto Fu","22","Kyoto Shi","1857906","Shimogyo Ku","26106","34.95","135.8167","1"],"600-8414":["JP","600-8414","Nioitenjincho","Kyoto Fu","22","Kyoto Shi","1857906","Shimogyo Ku","26106","34.95","135.8167","1"],"600-8415":["JP","600-8415","Inabadocho","Kyoto Fu","22","Kyoto Shi","1857906","Shimogyo Ku","26106","34.95","135.8167","1"],"600-8416":["JP","600-8416","Yakushimaecho","Kyoto Fu","22","Kyoto Shi","1857906","Shimogyo Ku","26106","34.95","135.8167","1"],"600-8417":["JP","600-8417","Shunzeicho","Kyoto Fu","22","Kyoto Shi","1857906","Shimogyo Ku","26106","34.95","135.8167","1"],"600-8418":["JP","600-8418","Gojokarasumacho","Kyoto Fu","22","Kyoto Shi","1857906","Shimogyo Ku","26106","34.95","135.8167","1"],"600-8419":["JP","600-8419","Oboricho","Kyoto Fu","22","Kyoto Shi","1857906","Shimogyo Ku","26106","34.95","135.8167","1"],"600-8420":["JP","600-8420","Takasagocho","Kyoto Fu","22","Kyoto Shi","1857906","Shimogyo Ku","26106","34.95","135.8167","1"],"600-8421":["JP","600-8421","Dojishacho","Kyoto Fu","22","Kyoto Shi","1857906","Shimogyo Ku","26106","34.95","135.8167","1"],"600-8422":["JP","600-8422","Hakurakutencho","Kyoto Fu","22","Kyoto Shi","1857906","Shimogyo Ku","26106","34.95","135.8167","1"],"600-8423":["JP","600-8423","Kugikakushicho","Kyoto Fu","22","Kyoto Shi","1857906","Shimogyo Ku","26106","34.95","135.8167","1"],"600-8424":["JP","600-8424","Sannocho(Muromachidoritakatsujiagar","Kyoto Fu","22","Kyoto Shi","1857906","Shimogyo Ku","26106","34.95","135.8167","1"],"600-8425":["JP","600-8425","Honeyacho","Kyoto Fu","22","Kyoto Shi","1857906","Shimogyo Ku","26106","34.95","135.8167","1"],"600-8426":["JP","600-8426","Kojimacho","Kyoto Fu","22","Kyoto Shi","1857906","Shimogyo Ku","26106","34.95","135.8167","1"],"600-8427":["JP","600-8427","Tamatsushimacho","Kyoto Fu","22","Kyoto Shi","1857906","Shimogyo Ku","26106","34.95","135.8167","1"],"600-8428":["JP","600-8428","Benzaitencho","Kyoto Fu","22","Kyoto Shi","1857906","Shimogyo Ku","26106","34.95","135.8167","1"],"600-8429":["JP","600-8429","Gokuishicho","Kyoto Fu","22","Kyoto Shi","1857906","Shimogyo Ku","26106","34.95","135.8167","1"],"600-8430":["JP","600-8430","Odawaracho","Kyoto Fu","22","Kyoto Shi","1857906","Shimogyo Ku","26106","34.95","135.8167","1"],"600-8431":["JP","600-8431","Zenchojicho","Kyoto Fu","22","Kyoto Shi","1857906","Shimogyo Ku","26106","34.95","135.8167","1"],"600-8432":["JP","600-8432","Itoyacho","Kyoto Fu","22","Kyoto Shi","1857906","Shimogyo Ku","26106","34.95","135.8167","1"],"600-8433":["JP","600-8433","Hanjocho","Kyoto Fu","22","Kyoto Shi","1857906","Shimogyo Ku","26106","34.95","135.8167","1"],"600-8434":["JP","600-8434","Takatsujicho","Kyoto Fu","22","Kyoto Shi","1857906","Shimogyo Ku","26106","34.95","135.8167","1"],"600-8435":["JP","600-8435","Nakanonocho","Kyoto Fu","22","Kyoto Shi","1857906","Shimogyo Ku","26106","34.95","135.8167","1"],"600-8436":["JP","600-8436","Motoryogaecho","Kyoto Fu","22","Kyoto Shi","1857906","Shimogyo Ku","26106","34.95","135.8167","1"],"600-8437":["JP","600-8437","Tokumancho","Kyoto Fu","22","Kyoto Shi","1857906","Shimogyo Ku","26106","34.95","135.8167","1"],"600-8438":["JP","600-8438","Naginatagiricho","Kyoto Fu","22","Kyoto Shi","1857906","Shimogyo Ku","26106","34.95","135.8167","1"],"600-8439":["JP","600-8439","Bantoyacho","Kyoto Fu","22","Kyoto Shi","1857906","Shimogyo Ku","26106","34.95","135.8167","1"],"600-8440":["JP","600-8440","Zaimokucho","Kyoto Fu","22","Kyoto Shi","1857906","Shimogyo Ku","26106","34.95","135.8167","1"],"600-8441":["JP","600-8441","Shijocho","Kyoto Fu","22","Kyoto Shi","1857906","Shimogyo Ku","26106","34.95","135.8167","1"],"600-8442":["JP","600-8442","Yadacho","Kyoto Fu","22","Kyoto Shi","1857906","Shimogyo Ku","26106","34.95","135.8167","1"],"600-8443":["JP","600-8443","Funebokocho","Kyoto Fu","22","Kyoto Shi","1857906","Shimogyo Ku","26106","34.95","135.8167","1"],"600-8444":["JP","600-8444","Kandaijincho","Kyoto Fu","22","Kyoto Shi","1857906","Shimogyo Ku","26106","34.95","135.8167","1"],"600-8445":["JP","600-8445","Iwatoyamacho","Kyoto Fu","22","Kyoto Shi","1857906","Shimogyo Ku","26106","34.95","135.8167","1"],"600-8446":["JP","600-8446","Horinochicho","Kyoto Fu","22","Kyoto Shi","1857906","Shimogyo Ku","26106","34.95","135.8167","1"],"600-8447":["JP","600-8447","Mikagecho","Kyoto Fu","22","Kyoto Shi","1857906","Shimogyo Ku","26106","34.95","135.8167","1"],"600-8448":["JP","600-8448","Yabushitacho","Kyoto Fu","22","Kyoto Shi","1857906","Shimogyo Ku","26106","34.95","135.8167","1"],"600-8449":["JP","600-8449","Tominagacho","Kyoto Fu","22","Kyoto Shi","1857906","Shimogyo Ku","26106","34.95","135.8167","1"],"600-8451":["JP","600-8451","Kameyacho(Wakamiyadorimatsubarasaga","Kyoto Fu","22","Kyoto Shi","1857906","Shimogyo Ku","26106","34.95","135.8167","1"],"600-8452":["JP","600-8452","Nagakuracho","Kyoto Fu","22","Kyoto Shi","1857906","Shimogyo Ku","26106","34.95","135.8167","1"],"600-8453":["JP","600-8453","Tsukimicho","Kyoto Fu","22","Kyoto Shi","1857906","Shimogyo Ku","26106","34.95","135.8167","1"],"600-8454":["JP","600-8454","Nunoyacho","Kyoto Fu","22","Kyoto Shi","1857906","Shimogyo Ku","26106","34.95","135.8167","1"],"600-8455":["JP","600-8455","Yawatacho","Kyoto Fu","22","Kyoto Shi","1857906","Shimogyo Ku","26106","34.95","135.8167","1"],"600-8456":["JP","600-8456","Tenshitsukinuke(Chome)","Kyoto Fu","22","Kyoto Shi","1857906","Shimogyo Ku","26106","34.95","135.8167","1"],"600-8457":["JP","600-8457","Kamikanabutsucho","Kyoto Fu","22","Kyoto Shi","1857906","Shimogyo Ku","26106","34.95","135.8167","1"],"600-8458":["JP","600-8458","Higuchicho","Kyoto Fu","22","Kyoto Shi","1857906","Shimogyo Ku","26106","34.95","135.8167","1"],"600-8459":["JP","600-8459","Tenjimmaecho","Kyoto Fu","22","Kyoto Shi","1857906","Shimogyo Ku","26106","34.95","135.8167","1"],"600-8460":["JP","600-8460","Kojincho","Kyoto Fu","22","Kyoto Shi","1857906","Shimogyo Ku","26106","34.95","135.8167","1"],"600-8461":["JP","600-8461","Tokusayamacho","Kyoto Fu","22","Kyoto Shi","1857906","Shimogyo Ku","26106","34.95","135.8167","1"],"600-8462":["JP","600-8462","Honryusuicho","Kyoto Fu","22","Kyoto Shi","1857906","Shimogyo Ku","26106","34.95","135.8167","1"],"600-8463":["JP","600-8463","Eiyojicho","Kyoto Fu","22","Kyoto Shi","1857906","Shimogyo Ku","26106","34.95","135.8167","1"],"600-8464":["JP","600-8464","Kikuyacho","Kyoto Fu","22","Kyoto Shi","1857906","Shimogyo Ku","26106","34.95","135.8167","1"],"600-8465":["JP","600-8465","Takatsuji Nishinotoincho","Kyoto Fu","22","Kyoto Shi","1857906","Shimogyo Ku","26106","34.95","135.8167","1"],"600-8466":["JP","600-8466","Funayacho","Kyoto Fu","22","Kyoto Shi","1857906","Shimogyo Ku","26106","34.95","135.8167","1"],"600-8467":["JP","600-8467","Fumotocho","Kyoto Fu","22","Kyoto Shi","1857906","Shimogyo Ku","26106","34.95","135.8167","1"],"600-8468":["JP","600-8468","Sumiyoshicho","Kyoto Fu","22","Kyoto Shi","1857906","Shimogyo Ku","26106","34.95","135.8167","1"],"600-8469":["JP","600-8469","Taishiyamacho","Kyoto Fu","22","Kyoto Shi","1857906","Shimogyo Ku","26106","34.95","135.8167","1"],"600-8471":["JP","600-8471","Shinkamanzacho","Kyoto Fu","22","Kyoto Shi","1857906","Shimogyo Ku","26106","34.95","135.8167","1"],"600-8472":["JP","600-8472","Myodenjicho","Kyoto Fu","22","Kyoto Shi","1857906","Shimogyo Ku","26106","34.95","135.8167","1"],"600-8473":["JP","600-8473","Ashikariyamacho","Kyoto Fu","22","Kyoto Shi","1857906","Shimogyo Ku","26106","34.95","135.8167","1"],"600-8474":["JP","600-8474","Ayanishinotoincho","Kyoto Fu","22","Kyoto Shi","1857906","Shimogyo Ku","26106","34.95","135.8167","1"],"600-8475":["JP","600-8475","Kazahayacho","Kyoto Fu","22","Kyoto Shi","1857906","Shimogyo Ku","26106","34.95","135.8167","1"],"600-8476":["JP","600-8476","Kiyoshicho","Kyoto Fu","22","Kyoto Shi","1857906","Shimogyo Ku","26106","34.95","135.8167","1"],"600-8477":["JP","600-8477","Yohojicho","Kyoto Fu","22","Kyoto Shi","1857906","Shimogyo Ku","26106","34.95","135.8167","1"],"600-8478":["JP","600-8478","Nishiayanokoji Nishihancho","Kyoto Fu","22","Kyoto Shi","1857906","Shimogyo Ku","26106","34.95","135.8167","1"],"600-8479":["JP","600-8479","Nishiayanokoji Higashihancho","Kyoto Fu","22","Kyoto Shi","1857906","Shimogyo Ku","26106","34.95","135.8167","1"],"600-8480":["JP","600-8480","Koizumicho","Kyoto Fu","22","Kyoto Shi","1857906","Shimogyo Ku","26106","34.95","135.8167","1"],"600-8481":["JP","600-8481","Shijo Horikawacho","Kyoto Fu","22","Kyoto Shi","1857906","Shimogyo Ku","26106","34.95","135.8167","1"],"600-8482":["JP","600-8482","Ayahorikawacho","Kyoto Fu","22","Kyoto Shi","1857906","Shimogyo Ku","26106","34.95","135.8167","1"],"600-8483":["JP","600-8483","Yoshimizucho","Kyoto Fu","22","Kyoto Shi","1857906","Shimogyo Ku","26106","34.95","135.8167","1"],"600-8484":["JP","600-8484","Nishitakatsujicho","Kyoto Fu","22","Kyoto Shi","1857906","Shimogyo Ku","26106","34.95","135.8167","1"],"600-8485":["JP","600-8485","Gokencho","Kyoto Fu","22","Kyoto Shi","1857906","Shimogyo Ku","26106","34.95","135.8167","1"],"600-8486":["JP","600-8486","Takatsuji Horikawacho","Kyoto Fu","22","Kyoto Shi","1857906","Shimogyo Ku","26106","34.95","135.8167","1"],"600-8487":["JP","600-8487","Tachibanacho","Kyoto Fu","22","Kyoto Shi","1857906","Shimogyo Ku","26106","34.95","135.8167","1"],"600-8488":["JP","600-8488","Sasayacho","Kyoto Fu","22","Kyoto Shi","1857906","Shimogyo Ku","26106","34.95","135.8167","1"],"600-8489":["JP","600-8489","Hashitachibanacho","Kyoto Fu","22","Kyoto Shi","1857906","Shimogyo Ku","26106","34.95","135.8167","1"],"600-8490":["JP","600-8490","Tatsunakacho","Kyoto Fu","22","Kyoto Shi","1857906","Shimogyo Ku","26106","34.95","135.8167","1"],"600-8491":["JP","600-8491","Niwatoribokocho","Kyoto Fu","22","Kyoto Shi","1857906","Shimogyo Ku","26106","34.95","135.8167","1"],"600-8492":["JP","600-8492","Tsukihokocho","Kyoto Fu","22","Kyoto Shi","1857906","Shimogyo Ku","26106","34.95","135.8167","1"],"600-8493":["JP","600-8493","Katsukyoyamacho","Kyoto Fu","22","Kyoto Shi","1857906","Shimogyo Ku","26106","34.95","135.8167","1"],"600-8494":["JP","600-8494","Kasabokocho","Kyoto Fu","22","Kyoto Shi","1857906","Shimogyo Ku","26106","34.95","135.8167","1"],"600-8495":["JP","600-8495","Fujimotoyoricho","Kyoto Fu","22","Kyoto Shi","1857906","Shimogyo Ku","26106","34.95","135.8167","1"],"600-8496":["JP","600-8496","Ishiizutsucho","Kyoto Fu","22","Kyoto Shi","1857906","Shimogyo Ku","26106","34.95","135.8167","1"],"600-8497":["JP","600-8497","Koyadocho","Kyoto Fu","22","Kyoto Shi","1857906","Shimogyo Ku","26106","34.95","135.8167","1"],"600-8498":["JP","600-8498","Kashiwayacho","Kyoto Fu","22","Kyoto Shi","1857906","Shimogyo Ku","26106","34.95","135.8167","1"],"600-8499":["JP","600-8499","Karatsuyacho","Kyoto Fu","22","Kyoto Shi","1857906","Shimogyo Ku","26106","34.95","135.8167","1"],"600-8801":["JP","600-8801","Chudoji Nishideracho","Kyoto Fu","22","Kyoto Shi","1857906","Shimogyo Ku","26106","34.95","135.8167","1"],"600-8802":["JP","600-8802","Chudoji Kushigecho","Kyoto Fu","22","Kyoto Shi","1857906","Shimogyo Ku","26106","34.95","135.8167","1"],"600-8803":["JP","600-8803","Chudoji Yabunochicho","Kyoto Fu","22","Kyoto Shi","1857906","Shimogyo Ku","26106","34.95","135.8167","1"],"600-8804":["JP","600-8804","Chudoji Maedacho","Kyoto Fu","22","Kyoto Shi","1857906","Shimogyo Ku","26106","34.95","135.8167","1"],"600-8805":["JP","600-8805","Chudoji Kagitacho","Kyoto Fu","22","Kyoto Shi","1857906","Shimogyo Ku","26106","34.95","135.8167","1"],"600-8806":["JP","600-8806","Chudoji Mibugawacho","Kyoto Fu","22","Kyoto Shi","1857906","Shimogyo Ku","26106","34.95","135.8167","1"],"600-8807":["JP","600-8807","Chudoji Myobucho","Kyoto Fu","22","Kyoto Shi","1857906","Shimogyo Ku","26106","34.95","135.8167","1"],"600-8811":["JP","600-8811","Chudoji Bojocho","Kyoto Fu","22","Kyoto Shi","1857906","Shimogyo Ku","26106","34.95","135.8167","1"],"600-8812":["JP","600-8812","Chudoji Kitamachi","Kyoto Fu","22","Kyoto Shi","1857906","Shimogyo Ku","26106","34.95","135.8167","1"],"600-8813":["JP","600-8813","Chudoji Minamimachi","Kyoto Fu","22","Kyoto Shi","1857906","Shimogyo Ku","26106","34.95","135.8167","1"],"600-8814":["JP","600-8814","Chudoji Shonochicho","Kyoto Fu","22","Kyoto Shi","1857906","Shimogyo Ku","26106","34.95","135.8167","1"],"600-8815":["JP","600-8815","Chudoji Awatacho","Kyoto Fu","22","Kyoto Shi","1857906","Shimogyo Ku","26106","34.95","135.8167","1"],"600-8816":["JP","600-8816","Nishishinyashikichudojicho","Kyoto Fu","22","Kyoto Shi","1857906","Shimogyo Ku","26106","34.95","135.8167","1"],"600-8821":["JP","600-8821","Kosakacho","Kyoto Fu","22","Kyoto Shi","1857906","Shimogyo Ku","26106","34.95","135.8167","1"],"600-8822":["JP","600-8822","Urakatacho","Kyoto Fu","22","Kyoto Shi","1857906","Shimogyo Ku","26106","34.95","135.8167","1"],"600-8823":["JP","600-8823","Yakuencho","Kyoto Fu","22","Kyoto Shi","1857906","Shimogyo Ku","26106","34.95","135.8167","1"],"600-8824":["JP","600-8824","Ninintsukasacho","Kyoto Fu","22","Kyoto Shi","1857906","Shimogyo Ku","26106","34.95","135.8167","1"],"600-8825":["JP","600-8825","Nishishinyashikinakanocho","Kyoto Fu","22","Kyoto Shi","1857906","Shimogyo Ku","26106","34.95","135.8167","1"],"600-8826":["JP","600-8826","Nishishinyashikikaminocho","Kyoto Fu","22","Kyoto Shi","1857906","Shimogyo Ku","26106","34.95","135.8167","1"],"600-8827":["JP","600-8827","Nishishinyashikitayucho","Kyoto Fu","22","Kyoto Shi","1857906","Shimogyo Ku","26106","34.95","135.8167","1"],"600-8828":["JP","600-8828","Nishishinyashikiageyacho","Kyoto Fu","22","Kyoto Shi","1857906","Shimogyo Ku","26106","34.95","135.8167","1"],"600-8829":["JP","600-8829","Nishishinyashikishimonocho","Kyoto Fu","22","Kyoto Shi","1857906","Shimogyo Ku","26106","34.95","135.8167","1"],"600-8831":["JP","600-8831","Hanabatakecho","Kyoto Fu","22","Kyoto Shi","1857906","Shimogyo Ku","26106","34.95","135.8167","1"],"600-8832":["JP","600-8832","Suwabirakicho","Kyoto Fu","22","Kyoto Shi","1857906","Shimogyo Ku","26106","34.95","135.8167","1"],"600-8833":["JP","600-8833","Nishisuyacho","Kyoto Fu","22","Kyoto Shi","1857906","Shimogyo Ku","26106","34.95","135.8167","1"],"600-8834":["JP","600-8834","Wakicho","Kyoto Fu","22","Kyoto Shi","1857906","Shimogyo Ku","26106","34.95","135.8167","1"],"600-8835":["JP","600-8835","Kankijicho","Kyoto Fu","22","Kyoto Shi","1857906","Shimogyo Ku","26106","34.95","135.8167","1"],"600-8836":["JP","600-8836","Hachijobomoncho(Hachijodoriomiyanis","Kyoto Fu","22","Kyoto Shi","1857906","Shimogyo Ku","26106","34.95","135.8167","1"],"600-8837":["JP","600-8837","Ebisunobambacho","Kyoto Fu","22","Kyoto Shi","1857906","Shimogyo Ku","26106","34.95","135.8167","1"],"600-8841":["JP","600-8841","Sujaku Shokaicho","Kyoto Fu","22","Kyoto Shi","1857906","Shimogyo Ku","26106","34.95","135.8167","1"],"600-8842":["JP","600-8842","Sujaku Donokuchicho","Kyoto Fu","22","Kyoto Shi","1857906","Shimogyo Ku","26106","34.95","135.8167","1"],"600-8843":["JP","600-8843","Sujaku Uchihatacho","Kyoto Fu","22","Kyoto Shi","1857906","Shimogyo Ku","26106","34.95","135.8167","1"],"600-8844":["JP","600-8844","Sujaku Urahatacho","Kyoto Fu","22","Kyoto Shi","1857906","Shimogyo Ku","26106","34.95","135.8167","1"],"600-8845":["JP","600-8845","Sujaku Kitanokuchicho","Kyoto Fu","22","Kyoto Shi","1857906","Shimogyo Ku","26106","34.95","135.8167","1"],"600-8846":["JP","600-8846","Sujaku Hozocho","Kyoto Fu","22","Kyoto Shi","1857906","Shimogyo Ku","26106","34.95","135.8167","1"],"600-8847":["JP","600-8847","Sujaku Bunkicho","Kyoto Fu","22","Kyoto Shi","1857906","Shimogyo Ku","26106","34.95","135.8167","1"],"600-8851":["JP","600-8851","Umekoji Kashiracho","Kyoto Fu","22","Kyoto Shi","1857906","Shimogyo Ku","26106","34.95","135.8167","1"],"600-8852":["JP","600-8852","Umekoji Higashinakamachi","Kyoto Fu","22","Kyoto Shi","1857906","Shimogyo Ku","26106","34.95","135.8167","1"],"600-8853":["JP","600-8853","Umekoji Takahatacho","Kyoto Fu","22","Kyoto Shi","1857906","Shimogyo Ku","26106","34.95","135.8167","1"],"600-8854":["JP","600-8854","Umekoji Nishinakamachi","Kyoto Fu","22","Kyoto Shi","1857906","Shimogyo Ku","26106","34.95","135.8167","1"],"600-8855":["JP","600-8855","Umekoji Ishibashicho","Kyoto Fu","22","Kyoto Shi","1857906","Shimogyo Ku","26106","34.95","135.8167","1"],"600-8856":["JP","600-8856","Umekoji Hommachi","Kyoto Fu","22","Kyoto Shi","1857906","Shimogyo Ku","26106","34.95","135.8167","1"],"600-8857":["JP","600-8857","Umekoji Higashimachi","Kyoto Fu","22","Kyoto Shi","1857906","Shimogyo Ku","26106","34.95","135.8167","1"],"600-8861":["JP","600-8861","Shichijogoshonochi Kitamachi","Kyoto Fu","22","Kyoto Shi","1857906","Shimogyo Ku","26106","34.95","135.8167","1"],"600-8862":["JP","600-8862","Shichijogoshonochi Nakamachi","Kyoto Fu","22","Kyoto Shi","1857906","Shimogyo Ku","26106","34.95","135.8167","1"],"600-8863":["JP","600-8863","Shichijogoshonochi Hommachi","Kyoto Fu","22","Kyoto Shi","1857906","Shimogyo Ku","26106","34.95","135.8167","1"],"600-8864":["JP","600-8864","Shichijogoshonochi Minamimachi","Kyoto Fu","22","Kyoto Shi","1857906","Shimogyo Ku","26106","34.95","135.8167","1"],"600-8865":["JP","600-8865","Shichijogoshonochi Nishimachi","Kyoto Fu","22","Kyoto Shi","1857906","Shimogyo Ku","26106","34.95","135.8167","1"],"600-8871":["JP","600-8871","Nishishichijo Kitahigashinocho","Kyoto Fu","22","Kyoto Shi","1857906","Shimogyo Ku","26106","34.95","135.8167","1"],"600-8872":["JP","600-8872","Nishishichijo Minamihigashinocho","Kyoto Fu","22","Kyoto Shi","1857906","Shimogyo Ku","26106","34.95","135.8167","1"],"600-8873":["JP","600-8873","Nishishichijo Higashikubocho","Kyoto Fu","22","Kyoto Shi","1857906","Shimogyo Ku","26106","34.95","135.8167","1"],"600-8874":["JP","600-8874","Nishishichijo Nishikubocho","Kyoto Fu","22","Kyoto Shi","1857906","Shimogyo Ku","26106","34.95","135.8167","1"],"600-8875":["JP","600-8875","Nishishichijo Ishiicho","Kyoto Fu","22","Kyoto Shi","1857906","Shimogyo Ku","26106","34.95","135.8167","1"],"600-8876":["JP","600-8876","Nishishichijo Minaminakanocho","Kyoto Fu","22","Kyoto Shi","1857906","Shimogyo Ku","26106","34.95","135.8167","1"],"600-8877":["JP","600-8877","Nishishichijo Minaminishinocho","Kyoto Fu","22","Kyoto Shi","1857906","Shimogyo Ku","26106","34.95","135.8167","1"],"600-8878":["JP","600-8878","Nishishichijo Kitanishinocho","Kyoto Fu","22","Kyoto Shi","1857906","Shimogyo Ku","26106","34.95","135.8167","1"],"600-8879":["JP","600-8879","Nishishichijo Nakanocho","Kyoto Fu","22","Kyoto Shi","1857906","Shimogyo Ku","26106","34.95","135.8167","1"],"600-8881":["JP","600-8881","Nishishichijo Kakegoshicho","Kyoto Fu","22","Kyoto Shi","1857906","Shimogyo Ku","26106","34.95","135.8167","1"],"600-8882":["JP","600-8882","Nishishichijo Hiwadacho","Kyoto Fu","22","Kyoto Shi","1857906","Shimogyo Ku","26106","34.95","135.8167","1"],"600-8883":["JP","600-8883","Nishishichijo Kitakinutacho","Kyoto Fu","22","Kyoto Shi","1857906","Shimogyo Ku","26106","34.95","135.8167","1"],"600-8884":["JP","600-8884","Nishishichijo Minamikinutacho","Kyoto Fu","22","Kyoto Shi","1857906","Shimogyo Ku","26106","34.95","135.8167","1"],"600-8885":["JP","600-8885","Nishishichijo Minamitsukiyomicho","Kyoto Fu","22","Kyoto Shi","1857906","Shimogyo Ku","26106","34.95","135.8167","1"],"600-8886":["JP","600-8886","Nishishichijo Kitatsukiyomicho","Kyoto Fu","22","Kyoto Shi","1857906","Shimogyo Ku","26106","34.95","135.8167","1"],"600-8887":["JP","600-8887","Nishishichijo Nakuracho","Kyoto Fu","22","Kyoto Shi","1857906","Shimogyo Ku","26106","34.95","135.8167","1"],"600-8888":["JP","600-8888","Nishishichijo Yawatacho","Kyoto Fu","22","Kyoto Shi","1857906","Shimogyo Ku","26106","34.95","135.8167","1"],"600-8891":["JP","600-8891","Nishishichijo Higashihattandacho","Kyoto Fu","22","Kyoto Shi","1857906","Shimogyo Ku","26106","34.95","135.8167","1"],"600-8892":["JP","600-8892","Nishishichijo Nishihattandacho","Kyoto Fu","22","Kyoto Shi","1857906","Shimogyo Ku","26106","34.95","135.8167","1"],"600-8893":["JP","600-8893","Nishishichijo Goryocho","Kyoto Fu","22","Kyoto Shi","1857906","Shimogyo Ku","26106","34.95","135.8167","1"],"600-8894":["JP","600-8894","Nishishichijo Ichibecho","Kyoto Fu","22","Kyoto Shi","1857906","Shimogyo Ku","26106","34.95","135.8167","1"],"600-8895":["JP","600-8895","Nishishichijo Higashiishigatsubocho","Kyoto Fu","22","Kyoto Shi","1857906","Shimogyo Ku","26106","34.95","135.8167","1"],"600-8896":["JP","600-8896","Nishishichijo Nishiishigatsubocho","Kyoto Fu","22","Kyoto Shi","1857906","Shimogyo Ku","26106","34.95","135.8167","1"],"600-8897":["JP","600-8897","Nishishichijo Ommaedacho","Kyoto Fu","22","Kyoto Shi","1857906","Shimogyo Ku","26106","34.95","135.8167","1"],"600-8898":["JP","600-8898","Nishishichijo Higashiommaedacho","Kyoto Fu","22","Kyoto Shi","1857906","Shimogyo Ku","26106","34.95","135.8167","1"],"600-8899":["JP","600-8899","Nishishichijo Akayashirocho","Kyoto Fu","22","Kyoto Shi","1857906","Shimogyo Ku","26106","34.95","135.8167","1"]}