{"917-0361":["JP","917-0361","Natasho Agehara","Fukui Ken","06","Oi Gun","1854517","Oi Cho","18483","35.7919","136.068","1"],"917-0362":["JP","917-0362","Natasho Nagatani","Fukui Ken","06","Oi Gun","1854517","Oi Cho","18483","35.7919","136.068","1"],"917-0363":["JP","917-0363","Natasho Ageno","Fukui Ken","06","Oi Gun","1854517","Oi Cho","18483","35.7919","136.068","1"],"917-0364":["JP","917-0364","Natasho Mushigano","Fukui Ken","06","Oi Gun","1854517","Oi Cho","18483","35.7919","136.068","1"],"917-0365":["JP","917-0365","Natasho Ogurahata","Fukui Ken","06","Oi Gun","1854517","Oi Cho","18483","35.7919","136.068","1"],"917-0371":["JP","917-0371","Natasho Ogura","Fukui Ken","06","Oi Gun","1854517","Oi Cho","18483","35.7919","136.068","1"],"917-0372":["JP","917-0372","Natasho Domoto","Fukui Ken","06","Oi Gun","1854517","Oi Cho","18483","35.7919","136.068","1"],"917-0373":["JP","917-0373","Natasho Somegatani","Fukui Ken","06","Oi Gun","1854517","Oi Cho","18483","35.7919","136.068","1"],"917-0374":["JP","917-0374","Natasho Naka","Fukui Ken","06","Oi Gun","1854517","Oi Cho","18483","35.7919","136.068","1"],"917-0375":["JP","917-0375","Natasho Notaoi","Fukui Ken","06","Oi Gun","1854517","Oi Cho","18483","35.7919","136.068","1"],"917-0381":["JP","917-0381","Natasho Mie","Fukui Ken","06","Oi Gun","1854517","Oi Cho","18483","35.7919","136.068","1"],"917-0382":["JP","917-0382","Natasho Hisasaka","Fukui Ken","06","Oi Gun","1854517","Oi Cho","18483","35.7919","136.068","1"],"917-0383":["JP","917-0383","Natasho Shimo","Fukui Ken","06","Oi Gun","1854517","Oi Cho","18483","35.7919","136.068","1"],"917-0384":["JP","917-0384","Natasho Nishidani","Fukui Ken","06","Oi Gun","1854517","Oi Cho","18483","35.7919","136.068","1"],"917-0385":["JP","917-0385","Natasho Igami","Fukui Ken","06","Oi Gun","1854517","Oi Cho","18483","35.7919","136.068","1"],"917-0386":["JP","917-0386","Natasho Kuchisakamoto","Fukui Ken","06","Oi Gun","1854517","Oi Cho","18483","35.7919","136.068","1"],"917-0387":["JP","917-0387","Natasho Okusakamoto","Fukui Ken","06","Oi Gun","1854517","Oi Cho","18483","35.7919","136.068","1"],"917-0000":["JP","917-0000","Ikanikeisaiganaibaai","Fukui Ken","06","Obama Shi","1854843","","","35.8511","136.0223","1"],"917-0001":["JP","917-0001","Fukutani","Fukui Ken","06","Obama Shi","1854843","","","35.8511","136.0223","1"],"917-0002":["JP","917-0002","Kitanagamachi","Fukui Ken","06","Obama Shi","1854843","","","35.8511","136.0223","1"],"917-0003":["JP","917-0003","Gakuencho","Fukui Ken","06","Obama Shi","1854843","","","35.8511","136.0223","1"],"917-0004":["JP","917-0004","Minato","Fukui Ken","06","Obama Shi","1854843","","","35.8511","136.0223","1"],"917-0005":["JP","917-0005","Itayamachi","Fukui Ken","06","Obama Shi","1854843","","","35.8511","136.0223","1"],"917-0006":["JP","917-0006","Komatsubara","Fukui Ken","06","Obama Shi","1854843","","","35.8511","136.0223","1"],"917-0007":["JP","917-0007","Nishinagamachi","Fukui Ken","06","Obama Shi","1854843","","","35.8511","136.0223","1"],"917-0008":["JP","917-0008","Shinkomatsubara","Fukui Ken","06","Obama Shi","1854843","","","35.8511","136.0223","1"],"917-0011":["JP","917-0011","Nago","Fukui Ken","06","Obama Shi","1854843","","","35.8511","136.0223","1"],"917-0012":["JP","917-0012","Kumano","Fukui Ken","06","Obama Shi","1854843","","","35.8511","136.0223","1"],"917-0013":["JP","917-0013","Taranosho","Fukui Ken","06","Obama Shi","1854843","","","35.8511","136.0223","1"],"917-0014":["JP","917-0014","Takatsuka","Fukui Ken","06","Obama Shi","1854843","","","35.8511","136.0223","1"],"917-0015":["JP","917-0015","Kurita","Fukui Ken","06","Obama Shi","1854843","","","35.8511","136.0223","1"],"917-0016":["JP","917-0016","Tsugiyoshi","Fukui Ken","06","Obama Shi","1854843","","","35.8511","136.0223","1"],"917-0017":["JP","917-0017","Haga","Fukui Ken","06","Obama Shi","1854843","","","35.8511","136.0223","1"],"917-0018":["JP","917-0018","Matsugasaki","Fukui Ken","06","Obama Shi","1854843","","","35.8511","136.0223","1"],"917-0019":["JP","917-0019","Sannomae","Fukui Ken","06","Obama Shi","1854843","","","35.5114","135.7548","1"],"917-0021":["JP","917-0021","Tawara","Fukui Ken","06","Obama Shi","1854843","","","35.8511","136.0223","1"],"917-0022":["JP","917-0022","Kamitawara","Fukui Ken","06","Obama Shi","1854843","","","35.8511","136.0223","1"],"917-0023":["JP","917-0023","Fuchu","Fukui Ken","06","Obama Shi","1854843","","","35.8511","136.0223","1"],"917-0024":["JP","917-0024","Wakuri","Fukui Ken","06","Obama Shi","1854843","","","35.8511","136.0223","1"],"917-0025":["JP","917-0025","Kizaki","Fukui Ken","06","Obama Shi","1854843","","","35.8511","136.0223","1"],"917-0026":["JP","917-0026","Tada","Fukui Ken","06","Obama Shi","1854843","","","35.8511","136.0223","1"],"917-0027":["JP","917-0027","Igomori","Fukui Ken","06","Obama Shi","1854843","","","35.8511","136.0223","1"],"917-0028":["JP","917-0028","Nodai","Fukui Ken","06","Obama Shi","1854843","","","35.8511","136.0223","1"],"917-0031":["JP","917-0031","Yatabe","Fukui Ken","06","Obama Shi","1854843","","","35.4534","135.7107","1"],"917-0032":["JP","917-0032","Ozaki","Fukui Ken","06","Obama Shi","1854843","","","35.4534","135.7107","1"],"917-0033":["JP","917-0033","Suno","Fukui Ken","06","Obama Shi","1854843","","","35.4534","135.7107","1"],"917-0034":["JP","917-0034","Okudano","Fukui Ken","06","Obama Shi","1854843","","","35.4534","135.7107","1"],"917-0035":["JP","917-0035","Kuchidano","Fukui Ken","06","Obama Shi","1854843","","","35.4534","135.7107","1"],"917-0036":["JP","917-0036","Kaminakai","Fukui Ken","06","Obama Shi","1854843","","","35.4534","135.7107","3"],"917-0037":["JP","917-0037","Aioi","Fukui Ken","06","Obama Shi","1854843","","","35.4534","135.7107","1"],"917-0041":["JP","917-0041","Aoi","Fukui Ken","06","Obama Shi","1854843","","","36.1309","136.2176","1"],"917-0042":["JP","917-0042","Higashisei","Fukui Ken","06","Obama Shi","1854843","","","36.1309","136.2176","1"],"917-0043":["JP","917-0043","Nishisei","Fukui Ken","06","Obama Shi","1854843","","","36.1309","136.2176","1"],"917-0044":["JP","917-0044","Hansei","Fukui Ken","06","Obama Shi","1854843","","","36.0339","136.2663","3"],"917-0045":["JP","917-0045","Kamikado","Fukui Ken","06","Obama Shi","1854843","","","36.2279","136.1688","3"],"917-0046":["JP","917-0046","Okozu","Fukui Ken","06","Obama Shi","1854843","","","36.1309","136.2176","1"],"917-0047":["JP","917-0047","Koigawa","Fukui Ken","06","Obama Shi","1854843","","","36.1309","136.2176","1"],"917-0051":["JP","917-0051","Obama Shiratori","Fukui Ken","06","Obama Shi","1854843","","","35.8511","136.0223","1"],"917-0052":["JP","917-0052","Obama Otokoyama","Fukui Ken","06","Obama Shi","1854843","","","35.8511","136.0223","1"],"917-0053":["JP","917-0053","Obama Omiya","Fukui Ken","06","Obama Shi","1854843","","","35.8511","136.0223","1"],"917-0054":["JP","917-0054","Fushiwara","Fukui Ken","06","Obama Shi","1854843","","","35.8511","136.0223","1"],"917-0055":["JP","917-0055","Obama Asama","Fukui Ken","06","Obama Shi","1854843","","","35.8511","136.0223","1"],"917-0056":["JP","917-0056","Obama Ohara","Fukui Ken","06","Obama Shi","1854843","","","35.8511","136.0223","1"],"917-0057":["JP","917-0057","Obama Asuka","Fukui Ken","06","Obama Shi","1854843","","","35.8511","136.0223","1"],"917-0058":["JP","917-0058","Obama Katori","Fukui Ken","06","Obama Shi","1854843","","","35.8511","136.0223","1"],"917-0059":["JP","917-0059","Obama Kifune","Fukui Ken","06","Obama Shi","1854843","","","35.8511","136.0223","1"],"917-0061":["JP","917-0061","Obama Tamamae","Fukui Ken","06","Obama Shi","1854843","","","35.8511","136.0223","1"],"917-0062":["JP","917-0062","Obama Imamiya","Fukui Ken","06","Obama Shi","1854843","","","35.8511","136.0223","1"],"917-0063":["JP","917-0063","Obama Sakai","Fukui Ken","06","Obama Shi","1854843","","","35.8511","136.0223","1"],"917-0064":["JP","917-0064","Obama Tatsuta","Fukui Ken","06","Obama Shi","1854843","","","35.8511","136.0223","1"],"917-0065":["JP","917-0065","Obama Sumiyoshi","Fukui Ken","06","Obama Shi","1854843","","","35.8511","136.0223","1"],"917-0066":["JP","917-0066","Obama Kanda","Fukui Ken","06","Obama Shi","1854843","","","35.8511","136.0223","1"],"917-0067":["JP","917-0067","Obama Kashima","Fukui Ken","06","Obama Shi","1854843","","","35.8511","136.0223","1"],"917-0068":["JP","917-0068","Obama Hiyoshi","Fukui Ken","06","Obama Shi","1854843","","","35.8511","136.0223","1"],"917-0069":["JP","917-0069","Obama Shirahige","Fukui Ken","06","Obama Shi","1854843","","","35.8511","136.0223","1"],"917-0071":["JP","917-0071","Ichibancho","Fukui Ken","06","Obama Shi","1854843","","","35.8511","136.0223","1"],"917-0072":["JP","917-0072","Chigusa","Fukui Ken","06","Obama Shi","1854843","","","35.4991","135.7485","1"],"917-0073":["JP","917-0073","Yotsuyacho","Fukui Ken","06","Obama Shi","1854843","","","35.8511","136.0223","1"],"917-0074":["JP","917-0074","Nochisecho","Fukui Ken","06","Obama Shi","1854843","","","35.8511","136.0223","1"],"917-0075":["JP","917-0075","Minamigawacho","Fukui Ken","06","Obama Shi","1854843","","","35.8511","136.0223","1"],"917-0076":["JP","917-0076","Yunoka","Fukui Ken","06","Obama Shi","1854843","","","35.8511","136.0223","1"],"917-0077":["JP","917-0077","Ekimaecho","Fukui Ken","06","Obama Shi","1854843","","","35.8511","136.0223","1"],"917-0078":["JP","917-0078","Otecho","Fukui Ken","06","Obama Shi","1854843","","","35.8511","136.0223","1"],"917-0081":["JP","917-0081","Kawasaki","Fukui Ken","06","Obama Shi","1854843","","","35.469","135.7477","4"],"917-0082":["JP","917-0082","Obama Tsushima","Fukui Ken","06","Obama Shi","1854843","","","36.1954","136.1562","1"],"917-0083":["JP","917-0083","Obama Kiyotaki","Fukui Ken","06","Obama Shi","1854843","","","36.1954","136.1562","1"],"917-0084":["JP","917-0084","Obama Hiromine","Fukui Ken","06","Obama Shi","1854843","","","36.1954","136.1562","1"],"917-0085":["JP","917-0085","Obama Ikudama","Fukui Ken","06","Obama Shi","1854843","","","36.1954","136.1562","1"],"917-0086":["JP","917-0086","Obama Shiogama","Fukui Ken","06","Obama Shi","1854843","","","36.1954","136.1562","1"],"917-0087":["JP","917-0087","Obama Suzuka","Fukui Ken","06","Obama Shi","1854843","","","36.1954","136.1562","1"],"917-0088":["JP","917-0088","Obama Taga","Fukui Ken","06","Obama Shi","1854843","","","36.1954","136.1562","1"],"917-0091":["JP","917-0091","Nishizu","Fukui Ken","06","Obama Shi","1854843","","","35.5165","135.7523","4"],"917-0092":["JP","917-0092","Yamate","Fukui Ken","06","Obama Shi","1854843","","","35.5075","135.7534","1"],"917-0093":["JP","917-0093","Mizutori","Fukui Ken","06","Obama Shi","1854843","","","35.5049","135.7528","1"],"917-0094":["JP","917-0094","Maruyama","Fukui Ken","06","Obama Shi","1854843","","","35.469","135.7477","4"],"917-0095":["JP","917-0095","Jonai","Fukui Ken","06","Obama Shi","1854843","","","35.5037","135.746","1"],"917-0096":["JP","917-0096","Umpin","Fukui Ken","06","Obama Shi","1854843","","","35.5078","135.7482","1"],"917-0097":["JP","917-0097","Horiyashiki","Fukui Ken","06","Obama Shi","1854843","","","35.598","135.9159","1"],"917-0101":["JP","917-0101","Tagarasu","Fukui Ken","06","Obama Shi","1854843","","","35.5373","135.8355","4"],"917-0102":["JP","917-0102","Yashiro","Fukui Ken","06","Obama Shi","1854843","","","35.5373","135.8355","1"],"917-0103":["JP","917-0103","Shitsumi","Fukui Ken","06","Obama Shi","1854843","","","35.5373","135.8355","1"],"917-0104":["JP","917-0104","Inokuma","Fukui Ken","06","Obama Shi","1854843","","","35.5373","135.8355","1"],"917-0105":["JP","917-0105","Ano","Fukui Ken","06","Obama Shi","1854843","","","35.5373","135.8355","1"],"917-0106":["JP","917-0106","Anojiri","Fukui Ken","06","Obama Shi","1854843","","","35.5373","135.8355","1"],"917-0107":["JP","917-0107","Kogasaki","Fukui Ken","06","Obama Shi","1854843","","","35.5373","135.8355","1"],"917-0111":["JP","917-0111","Nishiogawa","Fukui Ken","06","Obama Shi","1854843","","","35.5396","135.719","1"],"917-0112":["JP","917-0112","Kao","Fukui Ken","06","Obama Shi","1854843","","","35.5396","135.719","1"],"917-0113":["JP","917-0113","Ugu","Fukui Ken","06","Obama Shi","1854843","","","35.5396","135.719","1"],"917-0114":["JP","917-0114","Wakasa","Fukui Ken","06","Obama Shi","1854843","","","35.5396","135.719","1"],"917-0115":["JP","917-0115","Hotokedani","Fukui Ken","06","Obama Shi","1854843","","","35.5396","135.719","1"],"917-0116":["JP","917-0116","Katsumi","Fukui Ken","06","Obama Shi","1854843","","","35.5396","135.719","4"],"917-0117":["JP","917-0117","Tomari","Fukui Ken","06","Obama Shi","1854843","","","35.5396","135.719","1"],"917-0221":["JP","917-0221","Otani","Fukui Ken","06","Obama Shi","1854843","","","35.469","135.7477","4"],"917-0222":["JP","917-0222","Shimbo","Fukui Ken","06","Obama Shi","1854843","","","35.8788","136.7147","1"],"917-0223":["JP","917-0223","Odo","Fukui Ken","06","Obama Shi","1854843","","","35.8788","136.7147","1"],"917-0224":["JP","917-0224","Takenaga","Fukui Ken","06","Obama Shi","1854843","","","35.8788","136.7147","1"],"917-0225":["JP","917-0225","Hombo","Fukui Ken","06","Obama Shi","1854843","","","35.8788","136.7147","1"],"917-0226":["JP","917-0226","Hirano","Fukui Ken","06","Obama Shi","1854843","","","35.8788","136.7147","1"],"917-0231":["JP","917-0231","Kokubu","Fukui Ken","06","Obama Shi","1854843","","","35.8298","136.2819","1"],"917-0232":["JP","917-0232","Toichiba","Fukui Ken","06","Obama Shi","1854843","","","35.8298","136.2819","1"],"917-0233":["JP","917-0233","Taikoji","Fukui Ken","06","Obama Shi","1854843","","","35.8298","136.2819","1"],"917-0234":["JP","917-0234","Ueno","Fukui Ken","06","Obama Shi","1854843","","","35.8298","136.2819","1"],"917-0235":["JP","917-0235","Shibuichi","Fukui Ken","06","Obama Shi","1854843","","","35.8298","136.2819","1"],"917-0236":["JP","917-0236","Sambuichi","Fukui Ken","06","Obama Shi","1854843","","","35.8298","136.2819","1"],"917-0237":["JP","917-0237","Monzen","Fukui Ken","06","Obama Shi","1854843","","","35.8298","136.2819","1"],"917-0238":["JP","917-0238","Ikenokochi","Fukui Ken","06","Obama Shi","1854843","","","35.8298","136.2819","1"],"917-0241":["JP","917-0241","Shima","Fukui Ken","06","Obama Shi","1854843","","","35.469","135.7477","4"],"917-0242":["JP","917-0242","Kanaya","Fukui Ken","06","Obama Shi","1854843","","","35.8135","136.1377","1"],"917-0243":["JP","917-0243","Ryuzen","Fukui Ken","06","Obama Shi","1854843","","","35.8135","136.1377","1"],"917-0244":["JP","917-0244","Jinguji","Fukui Ken","06","Obama Shi","1854843","","","35.8135","136.1377","1"],"917-0245":["JP","917-0245","Chuno","Fukui Ken","06","Obama Shi","1854843","","","35.8135","136.1377","1"],"917-0246":["JP","917-0246","Shimonegori","Fukui Ken","06","Obama Shi","1854843","","","35.8135","136.1377","1"],"917-0247":["JP","917-0247","Nakanohata","Fukui Ken","06","Obama Shi","1854843","","","35.8135","136.1377","1"],"917-0248":["JP","917-0248","Kaminegori","Fukui Ken","06","Obama Shi","1854843","","","35.8135","136.1377","1"],"917-0249":["JP","917-0249","Miyanomae","Fukui Ken","06","Obama Shi","1854843","","","35.8135","136.1377","1"],"917-0351":["JP","917-0351","Tamotani","Fukui Ken","06","Obama Shi","1854843","","","35.7919","136.068","1"],"917-0352":["JP","917-0352","Fukatani","Fukui Ken","06","Obama Shi","1854843","","","35.7919","136.068","1"],"917-0353":["JP","917-0353","Fukano","Fukui Ken","06","Obama Shi","1854843","","","35.7919","136.068","1"],"917-0354":["JP","917-0354","Wadata","Fukui Ken","06","Obama Shi","1854843","","","35.7919","136.068","1"],"917-0355":["JP","917-0355","Shimota","Fukui Ken","06","Obama Shi","1854843","","","35.7919","136.068","1"],"917-0356":["JP","917-0356","Kamita","Fukui Ken","06","Obama Shi","1854843","","","35.7919","136.068","1"],"917-0357":["JP","917-0357","Oya","Fukui Ken","06","Obama Shi","1854843","","","35.7919","136.068","1"]}